{"page":1,"rows":[{"id":"161726","cell":{"price_dt":"2016-04-18","base_fund_id":"161726","a_price":"0.974","a_price_increase_rt":"0.21%","a_profit_rt":"4.692%","a_amount":"2942","a_amount_increase":"2","a_amount_increase_rt":"0.068%","a_discount_rt":"4.040%","b_discount_rt":"4.456%","b_net_leverage_rt":"2.052","b_price_leverage_rt":"1.964","base_discount_rt":"0.101%","net_value":"0.9900","base_est_val":"0.9901","est_err":"0.01%"}},{"id":"161726","cell":{"price_dt":"2016-04-15","base_fund_id":"161726","a_price":"0.972","a_price_increase_rt":"-0.21%","a_profit_rt":"4.702%","a_amount":"2940","a_amount_increase":"-58","a_amount_increase_rt":"-1.935%","a_discount_rt":"4.240%","b_discount_rt":"3.290%","b_net_leverage_rt":"2.012","b_price_leverage_rt":"1.948","base_discount_rt":"-0.496%","net_value":"1.0090","base_est_val":"1.0120","est_err":"0.30%"}},{"id":"161726","cell":{"price_dt":"2016-04-14","base_fund_id":"161726","a_price":"0.974","a_price_increase_rt":"0.00%","a_profit_rt":"4.692%","a_amount":"2998","a_amount_increase":"161","a_amount_increase_rt":"5.675%","a_discount_rt":"4.040%","b_discount_rt":"3.271%","b_net_leverage_rt":"2.006","b_price_leverage_rt":"1.942","base_discount_rt":"-0.395%","net_value":"1.0120","base_est_val":"1.0123","est_err":"0.03%"}},{"id":"161726","cell":{"price_dt":"2016-04-13","base_fund_id":"161726","a_price":"0.974","a_price_increase_rt":"0.21%","a_profit_rt":"4.692%","a_amount":"2837","a_amount_increase":"19","a_amount_increase_rt":"0.674%","a_discount_rt":"4.040%","b_discount_rt":"2.587%","b_net_leverage_rt":"2.010","b_price_leverage_rt":"1.959","base_discount_rt":"-0.743%","net_value":"1.0100","base_est_val":"1.0100","est_err":"0.00%"}},{"id":"161726","cell":{"price_dt":"2016-04-12","base_fund_id":"161726","a_price":"0.972","a_price_increase_rt":"0.00%","a_profit_rt":"4.702%","a_amount":"2818","a_amount_increase":"-18","a_amount_increase_rt":"-0.635%","a_discount_rt":"4.240%","b_discount_rt":"4.954%","b_net_leverage_rt":"2.047","b_price_leverage_rt":"1.951","base_discount_rt":"0.252%","net_value":"0.9920","base_est_val":"0.9913","est_err":"-0.07%"}},{"id":"161726","cell":{"price_dt":"2016-04-11","base_fund_id":"161726","a_price":"0.972","a_price_increase_rt":"0.00%","a_profit_rt":"4.702%","a_amount":"2836","a_amount_increase":"83","a_amount_increase_rt":"3.015%","a_discount_rt":"4.240%","b_discount_rt":"3.487%","b_net_leverage_rt":"2.041","b_price_leverage_rt":"1.972","base_discount_rt":"-0.452%","net_value":"0.9950","base_est_val":"0.9954","est_err":"0.04%"}},{"id":"161726","cell":{"price_dt":"2016-04-08","base_fund_id":"161726","a_price":"0.972","a_price_increase_rt":"0.10%","a_profit_rt":"4.697%","a_amount":"2753","a_amount_increase":"17","a_amount_increase_rt":"0.621%","a_discount_rt":"4.140%","b_discount_rt":"4.013%","b_net_leverage_rt":"2.100","b_price_leverage_rt":"2.019","base_discount_rt":"-0.258%","net_value":"0.9680","base_est_val":"0.9675","est_err":"-0.05%"}},{"id":"161726","cell":{"price_dt":"2016-04-07","base_fund_id":"161726","a_price":"0.971","a_price_increase_rt":"0.10%","a_profit_rt":"4.702%","a_amount":"2736","a_amount_increase":"-152","a_amount_increase_rt":"-5.263%","a_discount_rt":"4.240%","b_discount_rt":"5.263%","b_net_leverage_rt":"2.067","b_price_leverage_rt":"1.964","base_discount_rt":"0.356%","net_value":"0.9820","base_est_val":"0.9823","est_err":"0.03%"}},{"id":"161726","cell":{"price_dt":"2016-04-06","base_fund_id":"161726","a_price":"0.970","a_price_increase_rt":"0.31%","a_profit_rt":"4.707%","a_amount":"2888","a_amount_increase":"-133","a_amount_increase_rt":"-4.403%","a_discount_rt":"4.340%","b_discount_rt":"2.761%","b_net_leverage_rt":"2.037","b_price_leverage_rt":"1.982","base_discount_rt":"-0.853%","net_value":"0.9960","base_est_val":"0.9956","est_err":"-0.04%"}},{"id":"161726","cell":{"price_dt":"2016-04-05","base_fund_id":"161726","a_price":"0.967","a_price_increase_rt":"0.10%","a_profit_rt":"4.722%","a_amount":"3021","a_amount_increase":"-7","a_amount_increase_rt":"-0.231%","a_discount_rt":"4.640%","b_discount_rt":"3.638%","b_net_leverage_rt":"2.054","b_price_leverage_rt":"1.982","base_discount_rt":"-0.607%","net_value":"0.9880","base_est_val":"0.9879","est_err":"-0.01%"}},{"id":"161726","cell":{"price_dt":"2016-04-01","base_fund_id":"161726","a_price":"0.966","a_price_increase_rt":"-0.21%","a_profit_rt":"4.722%","a_amount":"3028","a_amount_increase":"180","a_amount_increase_rt":"6.320%","a_discount_rt":"4.640%","b_discount_rt":"4.510%","b_net_leverage_rt":"2.114","b_price_leverage_rt":"2.023","base_discount_rt":"-0.312%","net_value":"0.9610","base_est_val":"0.9614","est_err":"0.04%"}},{"id":"161726","cell":{"price_dt":"2016-03-31","base_fund_id":"161726","a_price":"0.968","a_price_increase_rt":"-0.21%","a_profit_rt":"4.712%","a_amount":"2848","a_amount_increase":"512","a_amount_increase_rt":"21.918%","a_discount_rt":"4.440%","b_discount_rt":"6.054%","b_net_leverage_rt":"2.095","b_price_leverage_rt":"1.976","base_discount_rt":"0.568%","net_value":"0.9690","base_est_val":"0.9664","est_err":"-0.27%"}},{"id":"161726","cell":{"price_dt":"2016-03-30","base_fund_id":"161726","a_price":"0.970","a_price_increase_rt":"-0.41%","a_profit_rt":"4.702%","a_amount":"2336","a_amount_increase":"-","a_amount_increase_rt":"0.000%","a_discount_rt":"4.240%","b_discount_rt":"7.626%","b_net_leverage_rt":"2.088","b_price_leverage_rt":"1.940","base_discount_rt":"1.440%","net_value":"0.9720","base_est_val":"0.9673","est_err":"-0.48%"}},{"id":"161726","cell":{"price_dt":"2016-03-29","base_fund_id":"161726","a_price":"0.974","a_price_increase_rt":"0.21%","a_profit_rt":"4.683%","a_amount":"2336","a_amount_increase":"-2","a_amount_increase_rt":"-0.086%","a_discount_rt":"3.850%","b_discount_rt":"7.577%","b_net_leverage_rt":"2.163","b_price_leverage_rt":"2.011","base_discount_rt":"1.433%","net_value":"0.9420","base_est_val":"0.9385","est_err":"-0.37%"}},{"id":"161726","cell":{"price_dt":"2016-03-28","base_fund_id":"161726","a_price":"0.972","a_price_increase_rt":"-0.21%","a_profit_rt":"4.692%","a_amount":"2338","a_amount_increase":"8","a_amount_increase_rt":"0.343%","a_discount_rt":"4.050%","b_discount_rt":"7.886%","b_net_leverage_rt":"2.110","b_price_leverage_rt":"1.955","base_discount_rt":"1.610%","net_value":"0.9630","base_est_val":"0.9780","est_err":"1.56%"}},{"id":"161726","cell":{"price_dt":"2016-03-25","base_fund_id":"161726","a_price":"0.974","a_price_increase_rt":"0.10%","a_profit_rt":"4.678%","a_amount":"2330","a_amount_increase":"108","a_amount_increase_rt":"4.860%","a_discount_rt":"3.750%","b_discount_rt":"3.967%","b_net_leverage_rt":"2.056","b_price_leverage_rt":"1.978","base_discount_rt":"0.000%","net_value":"0.9850","base_est_val":"0.9849","est_err":"-0.01%"}},{"id":"161726","cell":{"price_dt":"2016-03-24","base_fund_id":"161726","a_price":"0.973","a_price_increase_rt":"-0.31%","a_profit_rt":"4.683%","a_amount":"2222","a_amount_increase":"-","a_amount_increase_rt":"0.000%","a_discount_rt":"3.850%","b_discount_rt":"7.660%","b_net_leverage_rt":"2.077","b_price_leverage_rt":"1.929","base_discount_rt":"1.691%","net_value":"0.9760","base_est_val":"0.9767","est_err":"0.07%"}},{"id":"161726","cell":{"price_dt":"2016-03-23","base_fund_id":"161726","a_price":"0.976","a_price_increase_rt":"0.10%","a_profit_rt":"4.668%","a_amount":"2222","a_amount_increase":"-","a_amount_increase_rt":"0.000%","a_discount_rt":"3.560%","b_discount_rt":"8.841%","b_net_leverage_rt":"2.028","b_price_leverage_rt":"1.864","base_discount_rt":"2.555%","net_value":"0.9980","base_est_val":"0.9980","est_err":"0.00%"}},{"id":"161726","cell":{"price_dt":"2016-03-22","base_fund_id":"161726","a_price":"0.975","a_price_increase_rt":"-0.10%","a_profit_rt":"4.673%","a_amount":"2222","a_amount_increase":"-1","a_amount_increase_rt":"-0.045%","a_discount_rt":"3.660%","b_discount_rt":"3.272%","b_net_leverage_rt":"2.035","b_price_leverage_rt":"1.970","base_discount_rt":"-0.251%","net_value":"0.9950","base_est_val":"0.9955","est_err":"0.05%"}},{"id":"161726","cell":{"price_dt":"2016-03-21","base_fund_id":"161726","a_price":"0.976","a_price_increase_rt":"-0.10%","a_profit_rt":"4.668%","a_amount":"2223","a_amount_increase":"-26","a_amount_increase_rt":"-1.156%","a_discount_rt":"3.560%","b_discount_rt":"4.908%","b_net_leverage_rt":"2.035","b_price_leverage_rt":"1.940","base_discount_rt":"0.603%","net_value":"0.9950","base_est_val":"0.9932","est_err":"-0.18%"}},{"id":"161726","cell":{"price_dt":"2016-03-18","base_fund_id":"161726","a_price":"0.977","a_price_increase_rt":"-0.41%","a_profit_rt":"4.663%","a_amount":"2249","a_amount_increase":"3","a_amount_increase_rt":"0.134%","a_discount_rt":"3.460%","b_discount_rt":"3.632%","b_net_leverage_rt":"2.081","b_price_leverage_rt":"2.008","base_discount_rt":"-0.051%","net_value":"0.9740","base_est_val":"0.9727","est_err":"-0.13%"}},{"id":"161726","cell":{"price_dt":"2016-03-17","base_fund_id":"161726","a_price":"0.981","a_price_increase_rt":"0.00%","a_profit_rt":"4.639%","a_amount":"2246","a_amount_increase":"27","a_amount_increase_rt":"1.217%","a_discount_rt":"2.970%","b_discount_rt":"1.938%","b_net_leverage_rt":"2.153","b_price_leverage_rt":"2.112","base_discount_rt":"-0.689%","net_value":"0.9440","base_est_val":"0.9426","est_err":"-0.15%"}},{"id":"161726","cell":{"price_dt":"2016-03-16","base_fund_id":"161726","a_price":"0.981","a_price_increase_rt":"0.20%","a_profit_rt":"4.639%","a_amount":"2219","a_amount_increase":"35","a_amount_increase_rt":"1.603%","a_discount_rt":"2.970%","b_discount_rt":"6.057%","b_net_leverage_rt":"2.250","b_price_leverage_rt":"2.121","base_discount_rt":"1.044%","net_value":"0.9100","base_est_val":"0.9097","est_err":"-0.03%"}},{"id":"161726","cell":{"price_dt":"2016-03-15","base_fund_id":"161726","a_price":"0.979","a_price_increase_rt":"0.00%","a_profit_rt":"4.649%","a_amount":"2184","a_amount_increase":"9","a_amount_increase_rt":"0.414%","a_discount_rt":"3.170%","b_discount_rt":"7.238%","b_net_leverage_rt":"2.220","b_price_leverage_rt":"2.070","base_discount_rt":"1.522%","net_value":"0.9200","base_est_val":"0.9206","est_err":"0.07%"}},{"id":"161726","cell":{"price_dt":"2016-03-14","base_fund_id":"161726","a_price":"0.979","a_price_increase_rt":"0.10%","a_profit_rt":"4.649%","a_amount":"2175","a_amount_increase":"-","a_amount_increase_rt":"0.000%","a_discount_rt":"3.170%","b_discount_rt":"8.163%","b_net_leverage_rt":"2.214","b_price_leverage_rt":"2.047","base_discount_rt":"1.952%","net_value":"0.9220","base_est_val":"0.9198","est_err":"-0.24%"}},{"id":"161726","cell":{"price_dt":"2016-03-11","base_fund_id":"161726","a_price":"0.978","a_price_increase_rt":"0.10%","a_profit_rt":"4.654%","a_amount":"2175","a_amount_increase":"-","a_amount_increase_rt":"0.000%","a_discount_rt":"3.260%","b_discount_rt":"11.432%","b_net_leverage_rt":"2.329","b_price_leverage_rt":"2.090","base_discount_rt":"3.047%","net_value":"0.8860","base_est_val":"0.8857","est_err":"-0.03%"}},{"id":"161726","cell":{"price_dt":"2016-03-10","base_fund_id":"161726","a_price":"0.977","a_price_increase_rt":"0.21%","a_profit_rt":"4.658%","a_amount":"2175","a_amount_increase":"-","a_amount_increase_rt":"0.000%","a_discount_rt":"3.360%","b_discount_rt":"11.271%","b_net_leverage_rt":"2.325","b_price_leverage_rt":"2.090","base_discount_rt":"2.931%","net_value":"0.8870","base_est_val":"0.8880","est_err":"0.11%"}},{"id":"161726","cell":{"price_dt":"2016-03-09","base_fund_id":"161726","a_price":"0.975","a_price_increase_rt":"0.21%","a_profit_rt":"4.663%","a_amount":"2175","a_amount_increase":"-","a_amount_increase_rt":"0.000%","a_discount_rt":"3.470%","b_discount_rt":"6.468%","b_net_leverage_rt":"2.256","b_price_leverage_rt":"2.119","base_discount_rt":"0.937%","net_value":"0.9070","base_est_val":"0.9071","est_err":"0.01%"}},{"id":"161726","cell":{"price_dt":"2016-03-08","base_fund_id":"161726","a_price":"0.973","a_price_increase_rt":"0.10%","a_profit_rt":"4.673%","a_amount":"2175","a_amount_increase":"3","a_amount_increase_rt":"0.138%","a_discount_rt":"3.660%","b_discount_rt":"6.112%","b_net_leverage_rt":"2.235","b_price_leverage_rt":"2.106","base_discount_rt":"0.711%","net_value":"0.9140","base_est_val":"0.9140","est_err":"0.00%"}},{"id":"161726","cell":{"price_dt":"2016-03-07","base_fund_id":"161726","a_price":"0.972","a_price_increase_rt":"-0.10%","a_profit_rt":"4.678%","a_amount":"2172","a_amount_increase":"-","a_amount_increase_rt":"0.000%","a_discount_rt":"3.760%","b_discount_rt":"9.023%","b_net_leverage_rt":"2.266","b_price_leverage_rt":"2.078","base_discount_rt":"1.881%","net_value":"0.9040","base_est_val":"0.9028","est_err":"-0.13%"}},{"id":"161726","cell":{"price_dt":"2016-03-04","base_fund_id":"161726","a_price":"0.973","a_price_increase_rt":"0.31%","a_profit_rt":"4.673%","a_amount":"2172","a_amount_increase":"-","a_amount_increase_rt":"0.000%","a_discount_rt":"3.660%","b_discount_rt":"13.351%","b_net_leverage_rt":"2.322","b_price_leverage_rt":"2.048","base_discount_rt":"3.664%","net_value":"0.8870","base_est_val":"0.8869","est_err":"-0.01%"}},{"id":"161726","cell":{"price_dt":"2016-03-03","base_fund_id":"161726","a_price":"0.970","a_price_increase_rt":"-0.21%","a_profit_rt":"4.688%","a_amount":"2172","a_amount_increase":"2","a_amount_increase_rt":"0.092%","a_discount_rt":"3.960%","b_discount_rt":"4.513%","b_net_leverage_rt":"2.200","b_price_leverage_rt":"2.105","base_discount_rt":"-0.108%","net_value":"0.9260","base_est_val":"0.9217","est_err":"-0.46%"}},{"id":"161726","cell":{"price_dt":"2016-03-02","base_fund_id":"161726","a_price":"0.972","a_price_increase_rt":"0.00%","a_profit_rt":"4.678%","a_amount":"2170","a_amount_increase":"-","a_amount_increase_rt":"0.000%","a_discount_rt":"3.760%","b_discount_rt":"5.904%","b_net_leverage_rt":"2.217","b_price_leverage_rt":"2.093","base_discount_rt":"0.598%","net_value":"0.9200","base_est_val":"0.9138","est_err":"-0.67%"}},{"id":"161726","cell":{"price_dt":"2016-03-01","base_fund_id":"161726","a_price":"0.972","a_price_increase_rt":"0.10%","a_profit_rt":"4.673%","a_amount":"2170","a_amount_increase":"3","a_amount_increase_rt":"0.138%","a_discount_rt":"3.670%","b_discount_rt":"9.695%","b_net_leverage_rt":"2.340","b_price_leverage_rt":"2.133","base_discount_rt":"2.043%","net_value":"0.8810","base_est_val":"0.8776","est_err":"-0.39%"}},{"id":"161726","cell":{"price_dt":"2016-02-29","base_fund_id":"161726","a_price":"0.971","a_price_increase_rt":"-0.31%","a_profit_rt":"4.678%","a_amount":"2167","a_amount_increase":"-3","a_amount_increase_rt":"-0.138%","a_discount_rt":"3.770%","b_discount_rt":"10.340%","b_net_leverage_rt":"2.373","b_price_leverage_rt":"2.150","base_discount_rt":"2.179%","net_value":"0.8720","base_est_val":"0.8813","est_err":"1.07%"}},{"id":"161726","cell":{"price_dt":"2016-02-26","base_fund_id":"161726","a_price":"0.974","a_price_increase_rt":"-0.10%","a_profit_rt":"4.663%","a_amount":"2170","a_amount_increase":"-1","a_amount_increase_rt":"-0.046%","a_discount_rt":"3.470%","b_discount_rt":"6.930%","b_net_leverage_rt":"2.205","b_price_leverage_rt":"2.063","base_discount_rt":"1.246%","net_value":"0.9230","base_est_val":"0.9256","est_err":"0.28%"}},{"id":"161726","cell":{"price_dt":"2016-02-25","base_fund_id":"161726","a_price":"0.975","a_price_increase_rt":"-0.41%","a_profit_rt":"4.658%","a_amount":"2171","a_amount_increase":"-16","a_amount_increase_rt":"-0.732%","a_discount_rt":"3.370%","b_discount_rt":"7.574%","b_net_leverage_rt":"2.194","b_price_leverage_rt":"2.040","base_discount_rt":"1.618%","net_value":"0.9270","base_est_val":"0.9347","est_err":"0.83%"}},{"id":"161726","cell":{"price_dt":"2016-02-24","base_fund_id":"161726","a_price":"0.979","a_price_increase_rt":"0.00%","a_profit_rt":"4.639%","a_amount":"2187","a_amount_increase":"-6","a_amount_increase_rt":"-0.274%","a_discount_rt":"2.970%","b_discount_rt":"1.933%","b_net_leverage_rt":"2.026","b_price_leverage_rt":"1.988","base_discount_rt":"-0.552%","net_value":"0.9960","base_est_val":"0.9968","est_err":"0.08%"}},{"id":"161726","cell":{"price_dt":"2016-02-23","base_fund_id":"161726","a_price":"0.979","a_price_increase_rt":"0.31%","a_profit_rt":"4.639%","a_amount":"2193","a_amount_increase":"-1","a_amount_increase_rt":"-0.046%","a_discount_rt":"2.970%","b_discount_rt":"1.611%","b_net_leverage_rt":"2.016","b_price_leverage_rt":"1.984","base_discount_rt":"-0.699%","net_value":"1.0010","base_est_val":"1.0011","est_err":"0.01%"}},{"id":"161726","cell":{"price_dt":"2016-02-22","base_fund_id":"161726","a_price":"0.976","a_price_increase_rt":"0.10%","a_profit_rt":"4.654%","a_amount":"2194","a_amount_increase":"-4","a_amount_increase_rt":"-0.182%","a_discount_rt":"3.270%","b_discount_rt":"2.703%","b_net_leverage_rt":"2.010","b_price_leverage_rt":"1.957","base_discount_rt":"-0.299%","net_value":"1.0040","base_est_val":"1.0029","est_err":"-0.11%"}},{"id":"161726","cell":{"price_dt":"2016-02-19","base_fund_id":"161726","a_price":"0.975","a_price_increase_rt":"0.21%","a_profit_rt":"4.654%","a_amount":"2198","a_amount_increase":"-14","a_amount_increase_rt":"-0.633%","a_discount_rt":"3.270%","b_discount_rt":"3.484%","b_net_leverage_rt":"2.033","b_price_leverage_rt":"1.964","base_discount_rt":"0.050%","net_value":"0.9920","base_est_val":"0.9921","est_err":"0.01%"}},{"id":"161726","cell":{"price_dt":"2016-02-18","base_fund_id":"161726","a_price":"0.973","a_price_increase_rt":"-0.21%","a_profit_rt":"4.663%","a_amount":"2212","a_amount_increase":"-5","a_amount_increase_rt":"-0.226%","a_discount_rt":"3.470%","b_discount_rt":"2.680%","b_net_leverage_rt":"2.039","b_price_leverage_rt":"1.986","base_discount_rt":"-0.455%","net_value":"0.9890","base_est_val":"0.9892","est_err":"0.02%"}},{"id":"161726","cell":{"price_dt":"2016-02-17","base_fund_id":"161726","a_price":"0.975","a_price_increase_rt":"-0.10%","a_profit_rt":"4.654%","a_amount":"2217","a_amount_increase":"-8","a_amount_increase_rt":"-0.360%","a_discount_rt":"3.270%","b_discount_rt":"2.259%","b_net_leverage_rt":"2.035","b_price_leverage_rt":"1.990","base_discount_rt":"-0.555%","net_value":"0.9910","base_est_val":"0.9900","est_err":"-0.10%"}},{"id":"161726","cell":{"price_dt":"2016-02-16","base_fund_id":"161726","a_price":"0.976","a_price_increase_rt":"0.41%","a_profit_rt":"4.649%","a_amount":"2225","a_amount_increase":"-","a_amount_increase_rt":"0.000%","a_discount_rt":"3.170%","b_discount_rt":"2.391%","b_net_leverage_rt":"2.048","b_price_leverage_rt":"2.000","base_discount_rt":"-0.457%","net_value":"0.9850","base_est_val":"0.9836","est_err":"-0.14%"}},{"id":"161726","cell":{"price_dt":"2016-02-15","base_fund_id":"161726","a_price":"0.972","a_price_increase_rt":"-0.51%","a_profit_rt":"4.668%","a_amount":"2225","a_amount_increase":"2","a_amount_increase_rt":"0.090%","a_discount_rt":"3.570%","b_discount_rt":"3.146%","b_net_leverage_rt":"2.133","b_price_leverage_rt":"2.068","base_discount_rt":"-0.421%","net_value":"0.9490","base_est_val":"0.9492","est_err":"0.02%"}},{"id":"161726","cell":{"price_dt":"2016-02-05","base_fund_id":"161726","a_price":"0.977","a_price_increase_rt":"0.72%","a_profit_rt":"4.634%","a_amount":"2223","a_amount_increase":"-21","a_amount_increase_rt":"-0.936%","a_discount_rt":"2.880%","b_discount_rt":"4.392%","b_net_leverage_rt":"2.133","b_price_leverage_rt":"2.043","base_discount_rt":"0.528%","net_value":"0.9470","base_est_val":"0.9480","est_err":"0.11%"}},{"id":"161726","cell":{"price_dt":"2016-02-04","base_fund_id":"161726","a_price":"0.970","a_price_increase_rt":"0.10%","a_profit_rt":"4.668%","a_amount":"2244","a_amount_increase":"-22","a_amount_increase_rt":"-0.971%","a_discount_rt":"3.580%","b_discount_rt":"2.539%","b_net_leverage_rt":"2.110","b_price_leverage_rt":"2.058","base_discount_rt":"-0.680%","net_value":"0.9560","base_est_val":"0.9545","est_err":"-0.16%"}},{"id":"161726","cell":{"price_dt":"2016-02-03","base_fund_id":"161726","a_price":"0.969","a_price_increase_rt":"0.00%","a_profit_rt":"4.673%","a_amount":"2266","a_amount_increase":"-44","a_amount_increase_rt":"-1.905%","a_discount_rt":"3.680%","b_discount_rt":"3.944%","b_net_leverage_rt":"2.167","b_price_leverage_rt":"2.085","base_discount_rt":"-0.161%","net_value":"0.9340","base_est_val":"0.9349","est_err":"0.10%"}},{"id":"161726","cell":{"price_dt":"2016-02-02","base_fund_id":"161726","a_price":"0.969","a_price_increase_rt":"0.10%","a_profit_rt":"4.673%","a_amount":"2310","a_amount_increase":"-41","a_amount_increase_rt":"-1.744%","a_discount_rt":"3.680%","b_discount_rt":"1.373%","b_net_leverage_rt":"2.151","b_price_leverage_rt":"2.122","base_discount_rt":"-1.330%","net_value":"0.9400","base_est_val":"0.9390","est_err":"-0.11%"}},{"id":"161726","cell":{"price_dt":"2016-02-01","base_fund_id":"161726","a_price":"0.968","a_price_increase_rt":"1.04%","a_profit_rt":"4.678%","a_amount":"2351","a_amount_increase":"-6","a_amount_increase_rt":"-0.255%","a_discount_rt":"3.780%","b_discount_rt":"3.951%","b_net_leverage_rt":"2.242","b_price_leverage_rt":"2.157","base_discount_rt":"-0.330%","net_value":"0.9080","base_est_val":"0.9087","est_err":"0.08%"}},{"id":"161726","cell":{"price_dt":"2016-01-29","base_fund_id":"161726","a_price":"0.958","a_price_increase_rt":"0.10%","a_profit_rt":"4.727%","a_amount":"2357","a_amount_increase":"-34","a_amount_increase_rt":"-1.422%","a_discount_rt":"4.770%","b_discount_rt":"3.762%","b_net_leverage_rt":"2.221","b_price_leverage_rt":"2.140","base_discount_rt":"-0.929%","net_value":"0.9150","base_est_val":"0.9144","est_err":"-0.07%"}},{"id":"161726","cell":{"price_dt":"2016-01-28","base_fund_id":"161726","a_price":"0.957","a_price_increase_rt":"0.31%","a_profit_rt":"4.727%","a_amount":"2391","a_amount_increase":"-102","a_amount_increase_rt":"-4.091%","a_discount_rt":"4.780%","b_discount_rt":"8.453%","b_net_leverage_rt":"2.307","b_price_leverage_rt":"2.127","base_discount_rt":"0.958%","net_value":"0.8870","base_est_val":"0.8882","est_err":"0.14%"}},{"id":"161726","cell":{"price_dt":"2016-01-27","base_fund_id":"161726","a_price":"0.954","a_price_increase_rt":"-0.21%","a_profit_rt":"4.742%","a_amount":"2493","a_amount_increase":"2","a_amount_increase_rt":"0.080%","a_discount_rt":"5.070%","b_discount_rt":"6.288%","b_net_leverage_rt":"2.215","b_price_leverage_rt":"2.084","base_discount_rt":"0.055%","net_value":"0.9160","base_est_val":"0.9156","est_err":"-0.04%"}},{"id":"161726","cell":{"price_dt":"2016-01-26","base_fund_id":"161726","a_price":"0.956","a_price_increase_rt":"-0.10%","a_profit_rt":"4.732%","a_amount":"2491","a_amount_increase":"-","a_amount_increase_rt":"0.000%","a_discount_rt":"4.880%","b_discount_rt":"12.605%","b_net_leverage_rt":"2.206","b_price_leverage_rt":"1.959","base_discount_rt":"3.047%","net_value":"0.9190","base_est_val":"0.9212","est_err":"0.24%"}},{"id":"161726","cell":{"price_dt":"2016-01-25","base_fund_id":"161726","a_price":"0.957","a_price_increase_rt":"0.53%","a_profit_rt":"4.727%","a_amount":"2491","a_amount_increase":"-","a_amount_increase_rt":"0.000%","a_discount_rt":"4.780%","b_discount_rt":"6.359%","b_net_leverage_rt":"2.031","b_price_leverage_rt":"1.909","base_discount_rt":"0.707%","net_value":"0.9900","base_est_val":"0.9898","est_err":"-0.02%"}},{"id":"161726","cell":{"price_dt":"2016-01-22","base_fund_id":"161726","a_price":"0.952","a_price_increase_rt":"-0.52%","a_profit_rt":"4.752%","a_amount":"2491","a_amount_increase":"-7","a_amount_increase_rt":"-0.280%","a_discount_rt":"5.270%","b_discount_rt":"6.957%","b_net_leverage_rt":"2.044","b_price_leverage_rt":"1.911","base_discount_rt":"0.711%","net_value":"0.9840","base_est_val":"0.9856","est_err":"0.16%"}},{"id":"161726","cell":{"price_dt":"2016-01-21","base_fund_id":"161726","a_price":"0.957","a_price_increase_rt":"0.00%","a_profit_rt":"4.727%","a_amount":"2498","a_amount_increase":"3","a_amount_increase_rt":"0.120%","a_discount_rt":"4.780%","b_discount_rt":"7.482%","b_net_leverage_rt":"2.059","b_price_leverage_rt":"1.916","base_discount_rt":"1.177%","net_value":"0.9770","base_est_val":"0.9688","est_err":"-0.84%"}},{"id":"161726","cell":{"price_dt":"2016-01-20","base_fund_id":"161726","a_price":"0.957","a_price_increase_rt":"-0.10%","a_profit_rt":"4.722%","a_amount":"2495","a_amount_increase":"-","a_amount_increase_rt":"0.000%","a_discount_rt":"4.680%","b_discount_rt":"5.010%","b_net_leverage_rt":"2.027","b_price_leverage_rt":"1.930","base_discount_rt":"0.101%","net_value":"0.9910","base_est_val":"0.9921","est_err":"0.11%"}},{"id":"161726","cell":{"price_dt":"2016-01-19","base_fund_id":"161726","a_price":"0.958","a_price_increase_rt":"-0.31%","a_profit_rt":"4.717%","a_amount":"2495","a_amount_increase":"-","a_amount_increase_rt":"0.000%","a_discount_rt":"4.580%","b_discount_rt":"8.300%","b_net_leverage_rt":"2.016","b_price_leverage_rt":"1.862","base_discount_rt":"1.807%","net_value":"0.9960","base_est_val":"0.9937","est_err":"-0.23%"}},{"id":"161726","cell":{"price_dt":"2016-01-18","base_fund_id":"161726","a_price":"0.961","a_price_increase_rt":"-0.52%","a_profit_rt":"4.702%","a_amount":"2495","a_amount_increase":"-","a_amount_increase_rt":"0.000%","a_discount_rt":"4.280%","b_discount_rt":"10.044%","b_net_leverage_rt":"2.096","b_price_leverage_rt":"1.905","base_discount_rt":"2.552%","net_value":"0.9600","base_est_val":"0.9586","est_err":"-0.15%"}},{"id":"161726","cell":{"price_dt":"2016-01-15","base_fund_id":"161726","a_price":"0.966","a_price_increase_rt":"1.05%","a_profit_rt":"4.678%","a_amount":"2495","a_amount_increase":"-","a_amount_increase_rt":"0.000%","a_discount_rt":"3.780%","b_discount_rt":"9.932%","b_net_leverage_rt":"2.146","b_price_leverage_rt":"1.952","base_discount_rt":"2.606%","net_value":"0.9400","base_est_val":"0.9424","est_err":"0.26%"}},{"id":"161726","cell":{"price_dt":"2016-01-14","base_fund_id":"161726","a_price":"0.956","a_price_increase_rt":"-0.73%","a_profit_rt":"4.727%","a_amount":"2495","a_amount_increase":"2","a_amount_increase_rt":"0.080%","a_discount_rt":"4.780%","b_discount_rt":"9.509%","b_net_leverage_rt":"2.073","b_price_leverage_rt":"1.893","base_discount_rt":"2.113%","net_value":"0.9700","base_est_val":"0.9668","est_err":"-0.33%"}},{"id":"161726","cell":{"price_dt":"2016-01-13","base_fund_id":"161726","a_price":"0.963","a_price_increase_rt":"0.94%","a_profit_rt":"4.692%","a_amount":"2493","a_amount_increase":"-","a_amount_increase_rt":"0.000%","a_discount_rt":"4.080%","b_discount_rt":"14.554%","b_net_leverage_rt":"2.178","b_price_leverage_rt":"1.902","base_discount_rt":"4.472%","net_value":"0.9280","base_est_val":"0.9309","est_err":"0.31%"}},{"id":"161726","cell":{"price_dt":"2016-01-12","base_fund_id":"161726","a_price":"0.954","a_price_increase_rt":"0.53%","a_profit_rt":"4.732%","a_amount":"2493","a_amount_increase":"1","a_amount_increase_rt":"0.040%","a_discount_rt":"4.890%","b_discount_rt":"7.875%","b_net_leverage_rt":"2.082","b_price_leverage_rt":"1.930","base_discount_rt":"1.244%","net_value":"0.9650","base_est_val":"0.9648","est_err":"-0.02%"}},{"id":"161726","cell":{"price_dt":"2016-01-11","base_fund_id":"161726","a_price":"0.949","a_price_increase_rt":"1.17%","a_profit_rt":"4.757%","a_amount":"2492","a_amount_increase":"-3","a_amount_increase_rt":"-0.120%","a_discount_rt":"5.380%","b_discount_rt":"15.671%","b_net_leverage_rt":"2.131","b_price_leverage_rt":"1.842","base_discount_rt":"4.497%","net_value":"0.9450","base_est_val":"0.9497","est_err":"0.50%"}},{"id":"161726","cell":{"price_dt":"2016-01-08","base_fund_id":"161726","a_price":"0.938","a_price_increase_rt":"0.11%","a_profit_rt":"4.813%","a_amount":"2495","a_amount_increase":"-1","a_amount_increase_rt":"-0.040%","a_discount_rt":"6.480%","b_discount_rt":"10.787%","b_net_leverage_rt":"1.975","b_price_leverage_rt":"1.782","base_discount_rt":"2.264%","net_value":"1.0160","base_est_val":"1.0144","est_err":"-0.16%"}},{"id":"161726","cell":{"price_dt":"2016-01-07","base_fund_id":"161726","a_price":"0.937","a_price_increase_rt":"-0.11%","a_profit_rt":"4.818%","a_amount":"2496","a_amount_increase":"-20","a_amount_increase_rt":"-0.795%","a_discount_rt":"6.580%","b_discount_rt":"14.544%","b_net_leverage_rt":"2.006","b_price_leverage_rt":"1.751","base_discount_rt":"3.950%","net_value":"1.0000","base_est_val":"1.0071","est_err":"0.71%"}},{"id":"161726","cell":{"price_dt":"2016-01-06","base_fund_id":"161726","a_price":"0.938","a_price_increase_rt":"0.75%","a_profit_rt":"4.813%","a_amount":"2516","a_amount_increase":"15","a_amount_increase_rt":"0.600%","a_discount_rt":"6.480%","b_discount_rt":"6.150%","b_net_leverage_rt":"1.845","b_price_leverage_rt":"1.738","base_discount_rt":"0.365%","net_value":"1.0950","base_est_val":"1.0939","est_err":"-0.10%"}},{"id":"161726","cell":{"price_dt":"2016-01-05","base_fund_id":"161726","a_price":"0.931","a_price_increase_rt":"0.32%","a_profit_rt":"4.849%","a_amount":"2501","a_amount_increase":"-","a_amount_increase_rt":"0.000%","a_discount_rt":"7.180%","b_discount_rt":"8.472%","b_net_leverage_rt":"1.876","b_price_leverage_rt":"1.729","base_discount_rt":"1.164%","net_value":"1.0740","base_est_val":"1.0746","est_err":"0.06%"}},{"id":"161726","cell":{"price_dt":"2016-01-04","base_fund_id":"161726","a_price":"0.928","a_price_increase_rt":"-0.64%","a_profit_rt":"4.860%","a_amount":"2501","a_amount_increase":"1","a_amount_increase_rt":"0.040%","a_discount_rt":"7.390%","b_discount_rt":"12.205%","b_net_leverage_rt":"1.843","b_price_leverage_rt":"1.643","base_discount_rt":"3.242%","net_value":"1.0950","base_est_val":"1.1024","est_err":"0.68%"}},{"id":"161726","cell":{"price_dt":"2015-12-31","base_fund_id":"161726","a_price":"0.934","a_price_increase_rt":"0.54%","a_profit_rt":"4.828%","a_amount":"2500","a_amount_increase":"-","a_amount_increase_rt":"0.000%","a_discount_rt":"6.790%","b_discount_rt":"6.322%","b_net_leverage_rt":"1.720","b_price_leverage_rt":"1.618","base_discount_rt":"0.835%","net_value":"1.1970","base_est_val":"1.1980","est_err":"0.08%"}},{"id":"161726","cell":{"price_dt":"2015-12-30","base_fund_id":"161726","a_price":"0.929","a_price_increase_rt":"0.32%","a_profit_rt":"4.854%","a_amount":"2500","a_amount_increase":"-","a_amount_increase_rt":"0.000%","a_discount_rt":"7.290%","b_discount_rt":"4.775%","b_net_leverage_rt":"1.704","b_price_leverage_rt":"1.626","base_discount_rt":"-0.206%","net_value":"1.2130","base_est_val":"1.2113","est_err":"-0.14%"}},{"id":"161726","cell":{"price_dt":"2015-12-29","base_fund_id":"161726","a_price":"0.926","a_price_increase_rt":"-0.22%","a_profit_rt":"4.870%","a_amount":"2500","a_amount_increase":"-4","a_amount_increase_rt":"-0.160%","a_discount_rt":"7.580%","b_discount_rt":"5.862%","b_net_leverage_rt":"1.708","b_price_leverage_rt":"1.613","base_discount_rt":"0.289%","net_value":"1.2090","base_est_val":"1.2093","est_err":"0.02%"}},{"id":"161726","cell":{"price_dt":"2015-12-28","base_fund_id":"161726","a_price":"0.928","a_price_increase_rt":"0.43%","a_profit_rt":"4.860%","a_amount":"2504","a_amount_increase":"-18","a_amount_increase_rt":"-0.714%","a_discount_rt":"7.390%","b_discount_rt":"6.709%","b_net_leverage_rt":"1.708","b_price_leverage_rt":"1.600","base_discount_rt":"0.868%","net_value":"1.2090","base_est_val":"1.2098","est_err":"0.07%"}},{"id":"161726","cell":{"price_dt":"2015-12-25","base_fund_id":"161726","a_price":"0.924","a_price_increase_rt":"0.33%","a_profit_rt":"4.875%","a_amount":"2522","a_amount_increase":"-2","a_amount_increase_rt":"-0.079%","a_discount_rt":"7.690%","b_discount_rt":"4.672%","b_net_leverage_rt":"1.678","b_price_leverage_rt":"1.603","base_discount_rt":"-0.323%","net_value":"1.2390","base_est_val":"1.2422","est_err":"0.26%"}},{"id":"161726","cell":{"price_dt":"2015-12-24","base_fund_id":"161726","a_price":"0.921","a_price_increase_rt":"0.00%","a_profit_rt":"4.891%","a_amount":"2524","a_amount_increase":"-6","a_amount_increase_rt":"-0.237%","a_discount_rt":"7.990%","b_discount_rt":"5.209%","b_net_leverage_rt":"1.686","b_price_leverage_rt":"1.603","base_discount_rt":"-0.163%","net_value":"1.2300","base_est_val":"1.2312","est_err":"0.10%"}},{"id":"161726","cell":{"price_dt":"2015-12-23","base_fund_id":"161726","a_price":"0.921","a_price_increase_rt":"-0.11%","a_profit_rt":"4.891%","a_amount":"2530","a_amount_increase":"-48","a_amount_increase_rt":"-1.862%","a_discount_rt":"7.990%","b_discount_rt":"7.118%","b_net_leverage_rt":"1.699","b_price_leverage_rt":"1.586","base_discount_rt":"0.904%","net_value":"1.2170","base_est_val":"1.2173","est_err":"0.02%"}},{"id":"161726","cell":{"price_dt":"2015-12-22","base_fund_id":"161726","a_price":"0.922","a_price_increase_rt":"-0.11%","a_profit_rt":"4.886%","a_amount":"2578","a_amount_increase":"-25","a_amount_increase_rt":"-0.960%","a_discount_rt":"7.890%","b_discount_rt":"4.101%","b_net_leverage_rt":"1.684","b_price_leverage_rt":"1.618","base_discount_rt":"-0.771%","net_value":"1.2320","base_est_val":"1.2327","est_err":"0.06%"}},{"id":"161726","cell":{"price_dt":"2015-12-21","base_fund_id":"161726","a_price":"0.923","a_price_increase_rt":"0.33%","a_profit_rt":"4.881%","a_amount":"2603","a_amount_increase":"-14","a_amount_increase_rt":"-0.535%","a_discount_rt":"7.790%","b_discount_rt":"4.864%","b_net_leverage_rt":"1.696","b_price_leverage_rt":"1.617","base_discount_rt":"-0.328%","net_value":"1.2200","base_est_val":"1.2173","est_err":"-0.22%"}},{"id":"161726","cell":{"price_dt":"2015-12-18","base_fund_id":"161726","a_price":"0.920","a_price_increase_rt":"0.22%","a_profit_rt":"4.891%","a_amount":"2617","a_amount_increase":"8","a_amount_increase_rt":"0.307%","a_discount_rt":"8.000%","b_discount_rt":"5.764%","b_net_leverage_rt":"1.720","b_price_leverage_rt":"1.627","base_discount_rt":"0.000%","net_value":"1.1940","base_est_val":"1.1965","est_err":"0.21%"}},{"id":"161726","cell":{"price_dt":"2015-12-17","base_fund_id":"161726","a_price":"0.918","a_price_increase_rt":"-8.20%","a_profit_rt":"4.902%","a_amount":"2609","a_amount_increase":"-","a_amount_increase_rt":"0.000%","a_discount_rt":"8.200%","b_discount_rt":"6.148%","b_net_leverage_rt":"1.741","b_price_leverage_rt":"1.640","base_discount_rt":"0.043%","net_value":"1.1750","base_est_val":"1.1758","est_err":"0.07%"}},{"id":"161726","cell":{"price_dt":"2015-12-16","base_fund_id":"161726","a_price":"0.933","a_price_increase_rt":"0.00%","a_profit_rt":"4.823%","a_amount":"2609","a_amount_increase":"-","a_amount_increase_rt":"0.000%","a_discount_rt":"6.700%","b_discount_rt":"7.110%","b_net_leverage_rt":"1.757","b_price_leverage_rt":"1.640","base_discount_rt":"1.149%","net_value":"1.1612","base_est_val":"1.1612","est_err":"0.00%"}},{"id":"161726","cell":{"price_dt":"2015-12-15","base_fund_id":"161726","a_price":"0.933","a_price_increase_rt":"0.21%","a_profit_rt":"4.823%","a_amount":"2609","a_amount_increase":"-","a_amount_increase_rt":"0.000%","a_discount_rt":"6.700%","b_discount_rt":"7.546%","b_net_leverage_rt":"1.762","b_price_leverage_rt":"1.639","base_discount_rt":"1.384%","net_value":"1.1560","base_est_val":"1.1663","est_err":"0.89%"}},{"id":"161726","cell":{"price_dt":"2015-12-14","base_fund_id":"161726","a_price":"0.931","a_price_increase_rt":"-0.43%","a_profit_rt":"4.956%","a_amount":"2609","a_amount_increase":"-71","a_amount_increase_rt":"-2.649%","a_discount_rt":"8.990%","b_discount_rt":"10.361%","b_net_leverage_rt":"1.785","b_price_leverage_rt":"1.618","base_discount_rt":"1.849%","net_value":"1.1630","base_est_val":"1.1636","est_err":"0.05%"}},{"id":"161726","cell":{"price_dt":"2015-12-11","base_fund_id":"161726","a_price":"0.935","a_price_increase_rt":"-0.11%","a_profit_rt":"4.929%","a_amount":"2680","a_amount_increase":"-56","a_amount_increase_rt":"-2.047%","a_discount_rt":"8.510%","b_discount_rt":"6.299%","b_net_leverage_rt":"1.795","b_price_leverage_rt":"1.688","base_discount_rt":"-0.260%","net_value":"1.1540","base_est_val":"1.1539","est_err":"-0.01%"}},{"id":"161726","cell":{"price_dt":"2015-12-10","base_fund_id":"161726","a_price":"0.936","a_price_increase_rt":"0.21%","a_profit_rt":"4.924%","a_amount":"2736","a_amount_increase":"-6","a_amount_increase_rt":"-0.219%","a_discount_rt":"8.410%","b_discount_rt":"5.046%","b_net_leverage_rt":"1.781","b_price_leverage_rt":"1.696","base_discount_rt":"-0.858%","net_value":"1.1650","base_est_val":"1.1648","est_err":"-0.02%"}},{"id":"161726","cell":{"price_dt":"2015-12-09","base_fund_id":"161726","a_price":"0.934","a_price_increase_rt":"-0.32%","a_profit_rt":"4.935%","a_amount":"2742","a_amount_increase":"12","a_amount_increase_rt":"0.440%","a_discount_rt":"8.610%","b_discount_rt":"5.426%","b_net_leverage_rt":"1.792","b_price_leverage_rt":"1.700","base_discount_rt":"-0.779%","net_value":"1.1560","base_est_val":"1.1558","est_err":"-0.02%"}},{"id":"161726","cell":{"price_dt":"2015-12-08","base_fund_id":"161726","a_price":"0.937","a_price_increase_rt":"0.21%","a_profit_rt":"4.919%","a_amount":"2730","a_amount_increase":"-69","a_amount_increase_rt":"-2.465%","a_discount_rt":"8.320%","b_discount_rt":"7.143%","b_net_leverage_rt":"1.777","b_price_leverage_rt":"1.658","base_discount_rt":"0.385%","net_value":"1.1690","base_est_val":"1.1701","est_err":"0.09%"}},{"id":"161726","cell":{"price_dt":"2015-12-07","base_fund_id":"161726","a_price":"0.935","a_price_increase_rt":"0.97%","a_profit_rt":"4.930%","a_amount":"2799","a_amount_increase":"-13","a_amount_increase_rt":"-0.462%","a_discount_rt":"8.510%","b_discount_rt":"4.499%","b_net_leverage_rt":"1.742","b_price_leverage_rt":"1.667","base_discount_rt":"-1.042%","net_value":"1.2000","base_est_val":"1.1990","est_err":"-0.08%"}},{"id":"161726","cell":{"price_dt":"2015-12-04","base_fund_id":"161726","a_price":"0.926","a_price_increase_rt":"0.22%","a_profit_rt":"4.973%","a_amount":"2812","a_amount_increase":"-17","a_amount_increase_rt":"-0.601%","a_discount_rt":"9.300%","b_discount_rt":"5.337%","b_net_leverage_rt":"1.757","b_price_leverage_rt":"1.668","base_discount_rt":"-0.970%","net_value":"1.1850","base_est_val":"1.1850","est_err":"0.00%"}},{"id":"161726","cell":{"price_dt":"2015-12-03","base_fund_id":"161726","a_price":"0.924","a_price_increase_rt":"0.11%","a_profit_rt":"4.985%","a_amount":"2829","a_amount_increase":"2","a_amount_increase_rt":"0.071%","a_discount_rt":"9.500%","b_discount_rt":"6.004%","b_net_leverage_rt":"1.757","b_price_leverage_rt":"1.657","base_discount_rt":"-0.675%","net_value":"1.1850","base_est_val":"1.1850","est_err":"0.00%"}},{"id":"161726","cell":{"price_dt":"2015-12-02","base_fund_id":"161726","a_price":"0.923","a_price_increase_rt":"0.00%","a_profit_rt":"4.990%","a_amount":"2827","a_amount_increase":"-16","a_amount_increase_rt":"-0.563%","a_discount_rt":"9.600%","b_discount_rt":"8.041%","b_net_leverage_rt":"1.797","b_price_leverage_rt":"1.663","base_discount_rt":"0.217%","net_value":"1.1510","base_est_val":"1.1507","est_err":"-0.03%"}},{"id":"161726","cell":{"price_dt":"2015-12-01","base_fund_id":"161726","a_price":"0.923","a_price_increase_rt":"-0.11%","a_profit_rt":"4.991%","a_amount":"2843","a_amount_increase":"-78","a_amount_increase_rt":"-2.670%","a_discount_rt":"9.600%","b_discount_rt":"6.236%","b_net_leverage_rt":"1.786","b_price_leverage_rt":"1.681","base_discount_rt":"-0.733%","net_value":"1.1600","base_est_val":"1.1584","est_err":"-0.14%"}},{"id":"161726","cell":{"price_dt":"2015-11-30","base_fund_id":"161726","a_price":"0.924","a_price_increase_rt":"0.00%","a_profit_rt":"4.985%","a_amount":"2921","a_amount_increase":"-15","a_amount_increase_rt":"-0.511%","a_discount_rt":"9.500%","b_discount_rt":"4.950%","b_net_leverage_rt":"1.790","b_price_leverage_rt":"1.705","base_discount_rt":"-1.426%","net_value":"1.1570","base_est_val":"1.1573","est_err":"0.03%"}},{"id":"161726","cell":{"price_dt":"2015-11-27","base_fund_id":"161726","a_price":"0.924","a_price_increase_rt":"0.00%","a_profit_rt":"4.980%","a_amount":"2936","a_amount_increase":"-20","a_amount_increase_rt":"-0.677%","a_discount_rt":"9.410%","b_discount_rt":"7.032%","b_net_leverage_rt":"1.788","b_price_leverage_rt":"1.671","base_discount_rt":"-0.216%","net_value":"1.1570","base_est_val":"1.1597","est_err":"0.23%"}},{"id":"161726","cell":{"price_dt":"2015-11-26","base_fund_id":"161726","a_price":"0.924","a_price_increase_rt":"-0.11%","a_profit_rt":"4.980%","a_amount":"2956","a_amount_increase":"-52","a_amount_increase_rt":"-1.729%","a_discount_rt":"9.410%","b_discount_rt":"4.722%","b_net_leverage_rt":"1.708","b_price_leverage_rt":"1.631","base_discount_rt":"-1.138%","net_value":"1.2300","base_est_val":"1.2298","est_err":"-0.02%"}},{"id":"161726","cell":{"price_dt":"2015-11-25","base_fund_id":"161726","a_price":"0.925","a_price_increase_rt":"-0.11%","a_profit_rt":"4.975%","a_amount":"3008","a_amount_increase":"-84","a_amount_increase_rt":"-2.717%","a_discount_rt":"9.310%","b_discount_rt":"5.074%","b_net_leverage_rt":"1.690","b_price_leverage_rt":"1.608","base_discount_rt":"-0.801%","net_value":"1.2490","base_est_val":"1.2486","est_err":"-0.03%"}},{"id":"161726","cell":{"price_dt":"2015-11-24","base_fund_id":"161726","a_price":"0.926","a_price_increase_rt":"0.22%","a_profit_rt":"4.969%","a_amount":"3092","a_amount_increase":"-64","a_amount_increase_rt":"-2.028%","a_discount_rt":"9.220%","b_discount_rt":"4.539%","b_net_leverage_rt":"1.712","b_price_leverage_rt":"1.638","base_discount_rt":"-1.183%","net_value":"1.2260","base_est_val":"1.2262","est_err":"0.02%"}},{"id":"161726","cell":{"price_dt":"2015-11-23","base_fund_id":"161726","a_price":"0.924","a_price_increase_rt":"0.00%","a_profit_rt":"4.980%","a_amount":"3156","a_amount_increase":"-39","a_amount_increase_rt":"-1.221%","a_discount_rt":"9.410%","b_discount_rt":"6.134%","b_net_leverage_rt":"1.728","b_price_leverage_rt":"1.628","base_discount_rt":"-0.413%","net_value":"1.2110","base_est_val":"1.2118","est_err":"0.07%"}},{"id":"161726","cell":{"price_dt":"2015-11-20","base_fund_id":"161726","a_price":"0.924","a_price_increase_rt":"0.00%","a_profit_rt":"4.975%","a_amount":"3195","a_amount_increase":"-16","a_amount_increase_rt":"-0.498%","a_discount_rt":"9.320%","b_discount_rt":"5.584%","b_net_leverage_rt":"1.739","b_price_leverage_rt":"1.647","base_discount_rt":"-0.751%","net_value":"1.1990","base_est_val":"1.1981","est_err":"-0.08%"}},{"id":"161726","cell":{"price_dt":"2015-11-19","base_fund_id":"161726","a_price":"0.924","a_price_increase_rt":"0.11%","a_profit_rt":"4.975%","a_amount":"3211","a_amount_increase":"-31","a_amount_increase_rt":"-0.956%","a_discount_rt":"9.320%","b_discount_rt":"5.616%","b_net_leverage_rt":"1.743","b_price_leverage_rt":"1.651","base_discount_rt":"-0.753%","net_value":"1.1950","base_est_val":"1.1948","est_err":"-0.02%"}},{"id":"161726","cell":{"price_dt":"2015-11-18","base_fund_id":"161726","a_price":"0.923","a_price_increase_rt":"-0.11%","a_profit_rt":"4.981%","a_amount":"3242","a_amount_increase":"-44","a_amount_increase_rt":"-1.339%","a_discount_rt":"9.420%","b_discount_rt":"7.105%","b_net_leverage_rt":"1.770","b_price_leverage_rt":"1.653","base_discount_rt":"-0.085%","net_value":"1.1710","base_est_val":"1.1715","est_err":"0.04%"}},{"id":"161726","cell":{"price_dt":"2015-11-17","base_fund_id":"161726","a_price":"0.924","a_price_increase_rt":"-0.54%","a_profit_rt":"4.975%","a_amount":"3286","a_amount_increase":"-138","a_amount_increase_rt":"-4.030%","a_discount_rt":"9.320%","b_discount_rt":"5.664%","b_net_leverage_rt":"1.740","b_price_leverage_rt":"1.647","base_discount_rt":"-0.710%","net_value":"1.1980","base_est_val":"1.1979","est_err":"-0.01%"}},{"id":"161726","cell":{"price_dt":"2015-11-16","base_fund_id":"161726","a_price":"0.929","a_price_increase_rt":"-0.43%","a_profit_rt":"4.948%","a_amount":"3424","a_amount_increase":"-119","a_amount_increase_rt":"-3.359%","a_discount_rt":"8.830%","b_discount_rt":"4.388%","b_net_leverage_rt":"1.721","b_price_leverage_rt":"1.649","base_discount_rt":"-1.151%","net_value":"1.2160","base_est_val":"1.2158","est_err":"-0.02%"}},{"id":"161726","cell":{"price_dt":"2015-11-13","base_fund_id":"161726","a_price":"0.933","a_price_increase_rt":"0.43%","a_profit_rt":"4.921%","a_amount":"3543","a_amount_increase":"-106","a_amount_increase_rt":"-2.905%","a_discount_rt":"8.350%","b_discount_rt":"5.036%","b_net_leverage_rt":"1.732","b_price_leverage_rt":"1.649","base_discount_rt":"-0.623%","net_value":"1.2040","base_est_val":"1.2050","est_err":"0.08%"}},{"id":"161726","cell":{"price_dt":"2015-11-12","base_fund_id":"161726","a_price":"0.929","a_price_increase_rt":"0.76%","a_profit_rt":"4.943%","a_amount":"3649","a_amount_increase":"-94","a_amount_increase_rt":"-2.511%","a_discount_rt":"8.740%","b_discount_rt":"4.755%","b_net_leverage_rt":"1.712","b_price_leverage_rt":"1.634","base_discount_rt":"-0.858%","net_value":"1.2240","base_est_val":"1.2239","est_err":"-0.01%"}},{"id":"161726","cell":{"price_dt":"2015-11-11","base_fund_id":"161726","a_price":"0.922","a_price_increase_rt":"0.44%","a_profit_rt":"4.982%","a_amount":"3743","a_amount_increase":"3","a_amount_increase_rt":"0.080%","a_discount_rt":"9.430%","b_discount_rt":"2.034%","b_net_leverage_rt":"1.714","b_price_leverage_rt":"1.680","base_discount_rt":"-2.741%","net_value":"1.2220","base_est_val":"1.1976","est_err":"-2.00%"}},{"id":"161726","cell":{"price_dt":"2015-11-10","base_fund_id":"161726","a_price":"0.918","a_price_increase_rt":"0.22%","a_profit_rt":"5.004%","a_amount":"3740","a_amount_increase":"-2","a_amount_increase_rt":"-0.053%","a_discount_rt":"9.820%","b_discount_rt":"5.755%","b_net_leverage_rt":"1.761","b_price_leverage_rt":"1.665","base_discount_rt":"-0.976%","net_value":"1.1780","base_est_val":"1.1708","est_err":"-0.61%"}},{"id":"161726","cell":{"price_dt":"2015-11-09","base_fund_id":"161726","a_price":"0.916","a_price_increase_rt":"-1.61%","a_profit_rt":"5.015%","a_amount":"3742","a_amount_increase":"443","a_amount_increase_rt":"13.428%","a_discount_rt":"10.020%","b_discount_rt":"8.296%","b_net_leverage_rt":"1.761","b_price_leverage_rt":"1.626","base_discount_rt":"0.382%","net_value":"1.1780","base_est_val":"1.1761","est_err":"-0.16%"}},{"id":"161726","cell":{"price_dt":"2015-11-06","base_fund_id":"161726","a_price":"0.931","a_price_increase_rt":"-0.21%","a_profit_rt":"4.927%","a_amount":"3299","a_amount_increase":"-1","a_amount_increase_rt":"-0.030%","a_discount_rt":"8.460%","b_discount_rt":"8.672%","b_net_leverage_rt":"1.781","b_price_leverage_rt":"1.638","base_discount_rt":"1.164%","net_value":"1.1600","base_est_val":"1.1586","est_err":"-0.12%"}},{"id":"161726","cell":{"price_dt":"2015-11-05","base_fund_id":"161726","a_price":"0.933","a_price_increase_rt":"-0.85%","a_profit_rt":"4.917%","a_amount":"3300","a_amount_increase":"-","a_amount_increase_rt":"0.000%","a_discount_rt":"8.260%","b_discount_rt":"7.997%","b_net_leverage_rt":"1.805","b_price_leverage_rt":"1.672","base_discount_rt":"0.746%","net_value":"1.1400","base_est_val":"1.1407","est_err":"0.06%"}},{"id":"161726","cell":{"price_dt":"2015-11-04","base_fund_id":"161726","a_price":"0.941","a_price_increase_rt":"-0.74%","a_profit_rt":"4.874%","a_amount":"3300","a_amount_increase":"-33","a_amount_increase_rt":"-0.990%","a_discount_rt":"7.470%","b_discount_rt":"5.058%","b_net_leverage_rt":"1.791","b_price_leverage_rt":"1.705","base_discount_rt":"-0.478%","net_value":"1.1510","base_est_val":"1.1463","est_err":"-0.41%"}},{"id":"161726","cell":{"price_dt":"2015-11-03","base_fund_id":"161726","a_price":"0.948","a_price_increase_rt":"0.21%","a_profit_rt":"4.838%","a_amount":"3333","a_amount_increase":"-75","a_amount_increase_rt":"-2.201%","a_discount_rt":"6.780%","b_discount_rt":"4.511%","b_net_leverage_rt":"1.866","b_price_leverage_rt":"1.785","base_discount_rt":"-0.730%","net_value":"1.0960","base_est_val":"1.0960","est_err":"0.00%"}},{"id":"161726","cell":{"price_dt":"2015-11-02","base_fund_id":"161726","a_price":"0.946","a_price_increase_rt":"0.00%","a_profit_rt":"4.848%","a_amount":"3408","a_amount_increase":"-160","a_amount_increase_rt":"-4.484%","a_discount_rt":"6.980%","b_discount_rt":"6.405%","b_net_leverage_rt":"1.868","b_price_leverage_rt":"1.756","base_discount_rt":"0.183%","net_value":"1.0940","base_est_val":"1.1002","est_err":"0.57%"}},{"id":"161726","cell":{"price_dt":"2015-10-30","base_fund_id":"161726","a_price":"0.946","a_price_increase_rt":"0.21%","a_profit_rt":"4.843%","a_amount":"3568","a_amount_increase":"-76","a_amount_increase_rt":"-2.086%","a_discount_rt":"6.890%","b_discount_rt":"3.659%","b_net_leverage_rt":"1.826","b_price_leverage_rt":"1.762","base_discount_rt":"-1.113%","net_value":"1.1230","base_est_val":"1.1243","est_err":"0.12%"}},{"id":"161726","cell":{"price_dt":"2015-10-29","base_fund_id":"161726","a_price":"0.944","a_price_increase_rt":"0.11%","a_profit_rt":"4.854%","a_amount":"3644","a_amount_increase":"-301","a_amount_increase_rt":"-7.630%","a_discount_rt":"7.090%","b_discount_rt":"3.734%","b_net_leverage_rt":"1.825","b_price_leverage_rt":"1.759","base_discount_rt":"-1.157%","net_value":"1.1240","base_est_val":"1.1218","est_err":"-0.20%"}},{"id":"161726","cell":{"price_dt":"2015-10-28","base_fund_id":"161726","a_price":"0.943","a_price_increase_rt":"0.43%","a_profit_rt":"4.859%","a_amount":"3945","a_amount_increase":"-110","a_amount_increase_rt":"-2.713%","a_discount_rt":"7.190%","b_discount_rt":"4.167%","b_net_leverage_rt":"1.830","b_price_leverage_rt":"1.757","base_discount_rt":"-0.982%","net_value":"1.1200","base_est_val":"1.1257","est_err":"0.51%"}},{"id":"161726","cell":{"price_dt":"2015-10-27","base_fund_id":"161726","a_price":"0.939","a_price_increase_rt":"0.64%","a_profit_rt":"4.881%","a_amount":"4055","a_amount_increase":"693","a_amount_increase_rt":"20.613%","a_discount_rt":"7.580%","b_discount_rt":"4.806%","b_net_leverage_rt":"1.788","b_price_leverage_rt":"1.706","base_discount_rt":"-0.650%","net_value":"1.1530","base_est_val":"1.1522","est_err":"-0.07%"}},{"id":"161726","cell":{"price_dt":"2015-10-26","base_fund_id":"161726","a_price":"0.933","a_price_increase_rt":"0.11%","a_profit_rt":"4.913%","a_amount":"3362","a_amount_increase":"245","a_amount_increase_rt":"7.860%","a_discount_rt":"8.170%","b_discount_rt":"5.189%","b_net_leverage_rt":"1.799","b_price_leverage_rt":"1.710","base_discount_rt":"-0.743%","net_value":"1.1440","base_est_val":"1.1428","est_err":"-0.10%"}},{"id":"161726","cell":{"price_dt":"2015-10-23","base_fund_id":"161726","a_price":"0.932","a_price_increase_rt":"0.00%","a_profit_rt":"4.913%","a_amount":"3117","a_amount_increase":"4","a_amount_increase_rt":"0.128%","a_discount_rt":"8.180%","b_discount_rt":"8.275%","b_net_leverage_rt":"1.785","b_price_leverage_rt":"1.649","base_discount_rt":"1.040%","net_value":"1.1540","base_est_val":"1.1443","est_err":"-0.84%"}},{"id":"161726","cell":{"price_dt":"2015-10-22","base_fund_id":"161726","a_price":"0.932","a_price_increase_rt":"0.11%","a_profit_rt":"5.184%","a_amount":"3113","a_amount_increase":"-7","a_amount_increase_rt":"-0.224%","a_discount_rt":"8.180%","b_discount_rt":"8.913%","b_net_leverage_rt":"1.830","b_price_leverage_rt":"1.680","base_discount_rt":"1.162%","net_value":"1.1190","base_est_val":"1.1098","est_err":"-0.82%"}},{"id":"161726","cell":{"price_dt":"2015-10-21","base_fund_id":"161726","a_price":"0.931","a_price_increase_rt":"0.87%","a_profit_rt":"5.190%","a_amount":"3120","a_amount_increase":"-","a_amount_increase_rt":"0.000%","a_discount_rt":"8.280%","b_discount_rt":"8.222%","b_net_leverage_rt":"1.907","b_price_leverage_rt":"1.762","base_discount_rt":"0.375%","net_value":"1.0670","base_est_val":"1.0777","est_err":"1.00%"}},{"id":"161726","cell":{"price_dt":"2015-10-20","base_fund_id":"161726","a_price":"0.923","a_price_increase_rt":"0.54%","a_profit_rt":"5.236%","a_amount":"3120","a_amount_increase":"3","a_amount_increase_rt":"0.096%","a_discount_rt":"9.060%","b_discount_rt":"6.667%","b_net_leverage_rt":"1.857","b_price_leverage_rt":"1.741","base_discount_rt":"-0.591%","net_value":"1.1000","base_est_val":"1.0973","est_err":"-0.25%"}},{"id":"161726","cell":{"price_dt":"2015-10-19","base_fund_id":"161726","a_price":"0.918","a_price_increase_rt":"-0.11%","a_profit_rt":"5.265%","a_amount":"3117","a_amount_increase":"-149","a_amount_increase_rt":"-4.562%","a_discount_rt":"9.560%","b_discount_rt":"7.892%","b_net_leverage_rt":"1.880","b_price_leverage_rt":"1.743","base_discount_rt":"-0.277%","net_value":"1.0840","base_est_val":"1.0851","est_err":"0.10%"}},{"id":"161726","cell":{"price_dt":"2015-10-16","base_fund_id":"161726","a_price":"0.919","a_price_increase_rt":"-0.65%","a_profit_rt":"5.253%","a_amount":"3266","a_amount_increase":"-95","a_amount_increase_rt":"-2.827%","a_discount_rt":"9.370%","b_discount_rt":"6.768%","b_net_leverage_rt":"1.858","b_price_leverage_rt":"1.740","base_discount_rt":"-0.683%","net_value":"1.0980","base_est_val":"1.0958","est_err":"-0.20%"}},{"id":"161726","cell":{"price_dt":"2015-10-15","base_fund_id":"161726","a_price":"0.925","a_price_increase_rt":"-0.96%","a_profit_rt":"5.219%","a_amount":"3361","a_amount_increase":"-82","a_amount_increase_rt":"-2.382%","a_discount_rt":"8.780%","b_discount_rt":"4.348%","b_net_leverage_rt":"1.882","b_price_leverage_rt":"1.803","base_discount_rt":"-1.802%","net_value":"1.0820","base_est_val":"1.0680","est_err":"-1.29%"}},{"id":"161726","cell":{"price_dt":"2015-10-14","base_fund_id":"161726","a_price":"0.934","a_price_increase_rt":"0.11%","a_profit_rt":"5.168%","a_amount":"3443","a_amount_increase":"56","a_amount_increase_rt":"1.653%","a_discount_rt":"7.890%","b_discount_rt":"2.656%","b_net_leverage_rt":"1.929","b_price_leverage_rt":"1.879","base_discount_rt":"-2.422%","net_value":"1.0530","base_est_val":"1.0284","est_err":"-2.34%"}},{"id":"161726","cell":{"price_dt":"2015-10-13","base_fund_id":"161726","a_price":"0.933","a_price_increase_rt":"-0.53%","a_profit_rt":"5.173%","a_amount":"3387","a_amount_increase":"203","a_amount_increase_rt":"6.376%","a_discount_rt":"7.990%","b_discount_rt":"6.019%","b_net_leverage_rt":"1.939","b_price_leverage_rt":"1.829","base_discount_rt":"-0.764%","net_value":"1.0470","base_est_val":"1.0365","est_err":"-1.00%"}},{"id":"161726","cell":{"price_dt":"2015-10-12","base_fund_id":"161726","a_price":"0.938","a_price_increase_rt":"-0.42%","a_profit_rt":"5.145%","a_amount":"3184","a_amount_increase":"99","a_amount_increase_rt":"3.209%","a_discount_rt":"7.500%","b_discount_rt":"6.522%","b_net_leverage_rt":"1.958","b_price_leverage_rt":"1.839","base_discount_rt":"-0.338%","net_value":"1.0360","base_est_val":"1.0153","est_err":"-2.00%"}},{"id":"161726","cell":{"price_dt":"2015-10-09","base_fund_id":"161726","a_price":"0.942","a_price_increase_rt":"0.21%","a_profit_rt":"5.118%","a_amount":"3085","a_amount_increase":"2","a_amount_increase_rt":"0.065%","a_discount_rt":"7.010%","b_discount_rt":"5.822%","b_net_leverage_rt":"2.035","b_price_leverage_rt":"1.923","base_discount_rt":"-0.703%","net_value":"0.9960","base_est_val":"0.9926","est_err":"-0.34%"}},{"id":"161726","cell":{"price_dt":"2015-10-08","base_fund_id":"161726","a_price":"0.940","a_price_increase_rt":"-0.32%","a_profit_rt":"5.129%","a_amount":"3083","a_amount_increase":"2","a_amount_increase_rt":"0.065%","a_discount_rt":"7.210%","b_discount_rt":"7.539%","b_net_leverage_rt":"2.061","b_price_leverage_rt":"1.916","base_discount_rt":"-0.051%","net_value":"0.9840","base_est_val":"0.9683","est_err":"-1.60%"}},{"id":"161726","cell":{"price_dt":"2015-09-30","base_fund_id":"161726","a_price":"0.943","a_price_increase_rt":"0.53%","a_profit_rt":"5.107%","a_amount":"3081","a_amount_increase":"-8","a_amount_increase_rt":"-0.259%","a_discount_rt":"6.820%","b_discount_rt":"10.508%","b_net_leverage_rt":"2.169","b_price_leverage_rt":"1.962","base_discount_rt":"1.171%","net_value":"0.9390","base_est_val":"0.9393","est_err":"0.03%"}},{"id":"161726","cell":{"price_dt":"2015-09-29","base_fund_id":"161726","a_price":"0.938","a_price_increase_rt":"0.32%","a_profit_rt":"5.135%","a_amount":"3089","a_amount_increase":"-2","a_amount_increase_rt":"-0.065%","a_discount_rt":"7.310%","b_discount_rt":"8.469%","b_net_leverage_rt":"2.174","b_price_leverage_rt":"2.004","base_discount_rt":"-0.053%","net_value":"0.9370","base_est_val":"0.9419","est_err":"0.52%"}},{"id":"161726","cell":{"price_dt":"2015-09-28","base_fund_id":"161726","a_price":"0.935","a_price_increase_rt":"0.00%","a_profit_rt":"5.152%","a_amount":"3091","a_amount_increase":"-4","a_amount_increase_rt":"-0.129%","a_discount_rt":"7.610%","b_discount_rt":"6.250%","b_net_leverage_rt":"2.129","b_price_leverage_rt":"2.004","base_discount_rt":"-1.101%","net_value":"0.9540","base_est_val":"0.9492","est_err":"-0.50%"}},{"id":"161726","cell":{"price_dt":"2015-09-25","base_fund_id":"161726","a_price":"0.935","a_price_increase_rt":"0.11%","a_profit_rt":"5.147%","a_amount":"3095","a_amount_increase":"-1","a_amount_increase_rt":"-0.032%","a_discount_rt":"7.520%","b_discount_rt":"8.595%","b_net_leverage_rt":"2.174","b_price_leverage_rt":"2.002","base_discount_rt":"-0.107%","net_value":"0.9360","base_est_val":"0.9457","est_err":"1.04%"}},{"id":"161726","cell":{"price_dt":"2015-09-24","base_fund_id":"161726","a_price":"0.934","a_price_increase_rt":"0.00%","a_profit_rt":"5.152%","a_amount":"3096","a_amount_increase":"-4","a_amount_increase_rt":"-0.129%","a_discount_rt":"7.620%","b_discount_rt":"7.351%","b_net_leverage_rt":"2.093","b_price_leverage_rt":"1.950","base_discount_rt":"-0.465%","net_value":"0.9680","base_est_val":"0.9642","est_err":"-0.39%"}},{"id":"161726","cell":{"price_dt":"2015-09-23","base_fund_id":"161726","a_price":"0.934","a_price_increase_rt":"0.11%","a_profit_rt":"5.153%","a_amount":"3100","a_amount_increase":"-","a_amount_increase_rt":"0.000%","a_discount_rt":"7.620%","b_discount_rt":"8.361%","b_net_leverage_rt":"2.127","b_price_leverage_rt":"1.963","base_discount_rt":"-0.105%","net_value":"0.9540","base_est_val":"0.9603","est_err":"0.66%"}},{"id":"161726","cell":{"price_dt":"2015-09-22","base_fund_id":"161726","a_price":"0.933","a_price_increase_rt":"0.21%","a_profit_rt":"5.158%","a_amount":"3100","a_amount_increase":"-5","a_amount_increase_rt":"-0.161%","a_discount_rt":"7.720%","b_discount_rt":"7.684%","b_net_leverage_rt":"2.079","b_price_leverage_rt":"1.931","base_discount_rt":"-0.308%","net_value":"0.9740","base_est_val":"0.9709","est_err":"-0.32%"}},{"id":"161726","cell":{"price_dt":"2015-09-21","base_fund_id":"161726","a_price":"0.931","a_price_increase_rt":"-0.11%","a_profit_rt":"5.170%","a_amount":"3105","a_amount_increase":"-","a_amount_increase_rt":"0.000%","a_discount_rt":"7.910%","b_discount_rt":"9.817%","b_net_leverage_rt":"2.091","b_price_leverage_rt":"1.904","base_discount_rt":"0.568%","net_value":"0.9690","base_est_val":"0.9603","est_err":"-0.90%"}},{"id":"161726","cell":{"price_dt":"2015-09-18","base_fund_id":"161726","a_price":"0.932","a_price_increase_rt":"0.00%","a_profit_rt":"5.158%","a_amount":"3105","a_amount_increase":"-113","a_amount_increase_rt":"-3.511%","a_discount_rt":"7.720%","b_discount_rt":"6.522%","b_net_leverage_rt":"2.156","b_price_leverage_rt":"2.024","base_discount_rt":"-1.115%","net_value":"0.9420","base_est_val":"0.9373","est_err":"-0.50%"}},{"id":"161726","cell":{"price_dt":"2015-09-17","base_fund_id":"161726","a_price":"0.932","a_price_increase_rt":"0.43%","a_profit_rt":"5.159%","a_amount":"3218","a_amount_increase":"-3","a_amount_increase_rt":"-0.093%","a_discount_rt":"7.720%","b_discount_rt":"9.693%","b_net_leverage_rt":"2.194","b_price_leverage_rt":"2.000","base_discount_rt":"0.216%","net_value":"0.9280","base_est_val":"0.9379","est_err":"1.07%"}},{"id":"161726","cell":{"price_dt":"2015-09-16","base_fund_id":"161726","a_price":"0.928","a_price_increase_rt":"-0.75%","a_profit_rt":"5.181%","a_amount":"3221","a_amount_increase":"-48","a_amount_increase_rt":"-1.468%","a_discount_rt":"8.120%","b_discount_rt":"2.506%","b_net_leverage_rt":"2.150","b_price_leverage_rt":"2.098","base_discount_rt":"-3.178%","net_value":"0.9440","base_est_val":"0.9183","est_err":"-2.72%"}},{"id":"161726","cell":{"price_dt":"2015-09-15","base_fund_id":"161726","a_price":"0.935","a_price_increase_rt":"0.43%","a_profit_rt":"5.142%","a_amount":"3269","a_amount_increase":"-132","a_amount_increase_rt":"-3.881%","a_discount_rt":"7.430%","b_discount_rt":"11.444%","b_net_leverage_rt":"2.376","b_price_leverage_rt":"2.132","base_discount_rt":"0.516%","net_value":"0.8720","base_est_val":"0.8876","est_err":"1.79%"}},{"id":"161726","cell":{"price_dt":"2015-09-14","base_fund_id":"161726","a_price":"0.931","a_price_increase_rt":"0.32%","a_profit_rt":"5.164%","a_amount":"3401","a_amount_increase":"-62","a_amount_increase_rt":"-1.790%","a_discount_rt":"7.820%","b_discount_rt":"12.500%","b_net_leverage_rt":"2.250","b_price_leverage_rt":"2.000","base_discount_rt":"1.210%","net_value":"0.9090","base_est_val":"0.9268","est_err":"1.96%"}},{"id":"161726","cell":{"price_dt":"2015-09-11","base_fund_id":"161726","a_price":"0.928","a_price_increase_rt":"-0.11%","a_profit_rt":"5.176%","a_amount":"3463","a_amount_increase":"-66","a_amount_increase_rt":"-1.870%","a_discount_rt":"8.030%","b_discount_rt":"8.485%","b_net_leverage_rt":"2.084","b_price_leverage_rt":"1.921","base_discount_rt":"-0.103%","net_value":"0.9700","base_est_val":"0.9704","est_err":"0.04%"}},{"id":"161726","cell":{"price_dt":"2015-09-10","base_fund_id":"161726","a_price":"0.929","a_price_increase_rt":"0.00%","a_profit_rt":"5.170%","a_amount":"3529","a_amount_increase":"-67","a_amount_increase_rt":"-1.863%","a_discount_rt":"7.930%","b_discount_rt":"10.532%","b_net_leverage_rt":"2.096","b_price_leverage_rt":"1.896","base_discount_rt":"0.881%","net_value":"0.9650","base_est_val":"0.9710","est_err":"0.62%"}},{"id":"161726","cell":{"price_dt":"2015-09-09","base_fund_id":"161726","a_price":"0.929","a_price_increase_rt":"-0.11%","a_profit_rt":"5.170%","a_amount":"3596","a_amount_increase":"-5","a_amount_increase_rt":"-0.139%","a_discount_rt":"7.930%","b_discount_rt":"6.392%","b_net_leverage_rt":"2.093","b_price_leverage_rt":"1.967","base_discount_rt":"-1.087%","net_value":"0.9660","base_est_val":"0.9583","est_err":"-0.80%"}},{"id":"161726","cell":{"price_dt":"2015-09-08","base_fund_id":"161726","a_price":"0.930","a_price_increase_rt":"-1.80%","a_profit_rt":"5.165%","a_amount":"3601","a_amount_increase":"7","a_amount_increase_rt":"0.195%","a_discount_rt":"7.830%","b_discount_rt":"2.985%","b_net_leverage_rt":"2.158","b_price_leverage_rt":"2.096","base_discount_rt":"-2.819%","net_value":"0.9400","base_est_val":"0.9232","est_err":"-1.79%"}},{"id":"161726","cell":{"price_dt":"2015-09-07","base_fund_id":"161726","a_price":"0.947","a_price_increase_rt":"-0.11%","a_profit_rt":"5.071%","a_amount":"3594","a_amount_increase":"-483","a_amount_increase_rt":"-11.847%","a_discount_rt":"6.140%","b_discount_rt":"7.918%","b_net_leverage_rt":"2.289","b_price_leverage_rt":"2.121","base_discount_rt":"0.000%","net_value":"0.8960","base_est_val":"0.8934","est_err":"-0.29%"}},{"id":"161726","cell":{"price_dt":"2015-09-02","base_fund_id":"161726","a_price":"0.948","a_price_increase_rt":"0.64%","a_profit_rt":"5.060%","a_amount":"4077","a_amount_increase":"-34","a_amount_increase_rt":"-0.827%","a_discount_rt":"5.950%","b_discount_rt":"9.221%","b_net_leverage_rt":"2.309","b_price_leverage_rt":"2.114","base_discount_rt":"0.619%","net_value":"0.8890","base_est_val":"0.8900","est_err":"0.11%"}},{"id":"161726","cell":{"price_dt":"2015-09-01","base_fund_id":"161726","a_price":"0.942","a_price_increase_rt":"1.62%","a_profit_rt":"5.093%","a_amount":"4111","a_amount_increase":"-412","a_amount_increase_rt":"-9.109%","a_discount_rt":"6.550%","b_discount_rt":"12.628%","b_net_leverage_rt":"2.286","b_price_leverage_rt":"2.029","base_discount_rt":"1.842%","net_value":"0.8960","base_est_val":"0.9131","est_err":"1.91%"}},{"id":"161726","cell":{"price_dt":"2015-08-31","base_fund_id":"161726","a_price":"0.927","a_price_increase_rt":"2.43%","a_profit_rt":"5.177%","a_amount":"4523","a_amount_increase":"-464","a_amount_increase_rt":"-9.304%","a_discount_rt":"8.040%","b_discount_rt":"8.518%","b_net_leverage_rt":"2.115","b_price_leverage_rt":"1.949","base_discount_rt":"-0.209%","net_value":"0.9560","base_est_val":"0.9675","est_err":"1.20%"}},{"id":"161726","cell":{"price_dt":"2015-08-28","base_fund_id":"161726","a_price":"0.905","a_price_increase_rt":"0.22%","a_profit_rt":"5.298%","a_amount":"4987","a_amount_increase":"-816","a_amount_increase_rt":"-14.062%","a_discount_rt":"10.130%","b_discount_rt":"3.604%","b_net_leverage_rt":"2.008","b_price_leverage_rt":"1.938","base_discount_rt":"-3.290%","net_value":"1.0030","base_est_val":"0.9825","est_err":"-2.04%"}},{"id":"161726","cell":{"price_dt":"2015-08-27","base_fund_id":"161726","a_price":"0.903","a_price_increase_rt":"0.33%","a_profit_rt":"5.310%","a_amount":"5803","a_amount_increase":"-6","a_amount_increase_rt":"-0.103%","a_discount_rt":"10.330%","b_discount_rt":"6.426%","b_net_leverage_rt":"2.135","b_price_leverage_rt":"2.006","base_discount_rt":"-2.482%","net_value":"0.9470","base_est_val":"0.9315","est_err":"-1.64%"}},{"id":"161726","cell":{"price_dt":"2015-08-26","base_fund_id":"161726","a_price":"0.900","a_price_increase_rt":"-0.33%","a_profit_rt":"5.328%","a_amount":"5809","a_amount_increase":"-11","a_amount_increase_rt":"-0.189%","a_discount_rt":"10.630%","b_discount_rt":"23.478%","b_net_leverage_rt":"2.251","b_price_leverage_rt":"1.823","base_discount_rt":"4.525%","net_value":"0.9060","base_est_val":"0.9153","est_err":"1.03%"}},{"id":"161726","cell":{"price_dt":"2015-08-25","base_fund_id":"161726","a_price":"0.903","a_price_increase_rt":"0.78%","a_profit_rt":"5.310%","a_amount":"5820","a_amount_increase":"-5","a_amount_increase_rt":"-0.086%","a_discount_rt":"10.330%","b_discount_rt":"30.342%","b_net_leverage_rt":"2.189","b_price_leverage_rt":"1.679","base_discount_rt":"8.252%","net_value":"0.9270","base_est_val":"0.9577","est_err":"3.31%"}},{"id":"161726","cell":{"price_dt":"2015-08-24","base_fund_id":"161726","a_price":"0.896","a_price_increase_rt":"1.36%","a_profit_rt":"5.629%","a_amount":"5825","a_amount_increase":"4","a_amount_increase_rt":"0.069%","a_discount_rt":"11.020%","b_discount_rt":"19.474%","b_net_leverage_rt":"1.981","b_price_leverage_rt":"1.658","base_discount_rt":"4.376%","net_value":"1.0170","base_est_val":"1.0508","est_err":"3.32%"}},{"id":"161726","cell":{"price_dt":"2015-08-21","base_fund_id":"161726","a_price":"0.884","a_price_increase_rt":"-0.11%","a_profit_rt":"5.700%","a_amount":"5821","a_amount_increase":"-83","a_amount_increase_rt":"-1.406%","a_discount_rt":"12.130%","b_discount_rt":"10.454%","b_net_leverage_rt":"1.815","b_price_leverage_rt":"1.643","base_discount_rt":"0.312%","net_value":"1.1200","base_est_val":"1.1400","est_err":"1.79%"}},{"id":"161726","cell":{"price_dt":"2015-08-20","base_fund_id":"161726","a_price":"0.885","a_price_increase_rt":"1.14%","a_profit_rt":"5.693%","a_amount":"5904","a_amount_increase":"-4","a_amount_increase_rt":"-0.068%","a_discount_rt":"12.030%","b_discount_rt":"9.840%","b_net_leverage_rt":"1.733","b_price_leverage_rt":"1.578","base_discount_rt":"0.589%","net_value":"1.1890","base_est_val":"1.2067","est_err":"1.49%"}},{"id":"161726","cell":{"price_dt":"2015-08-19","base_fund_id":"161726","a_price":"0.875","a_price_increase_rt":"-0.57%","a_profit_rt":"5.759%","a_amount":"5908","a_amount_increase":"-310","a_amount_increase_rt":"-4.986%","a_discount_rt":"13.020%","b_discount_rt":"6.192%","b_net_leverage_rt":"1.670","b_price_leverage_rt":"1.572","base_discount_rt":"-1.515%","net_value":"1.2540","base_est_val":"1.2393","est_err":"-1.17%"}},{"id":"161726","cell":{"price_dt":"2015-08-18","base_fund_id":"161726","a_price":"0.880","a_price_increase_rt":"0.69%","a_profit_rt":"5.726%","a_amount":"6218","a_amount_increase":"-156","a_amount_increase_rt":"-2.447%","a_discount_rt":"12.520%","b_discount_rt":"11.103%","b_net_leverage_rt":"1.711","b_price_leverage_rt":"1.540","base_discount_rt":"1.281%","net_value":"1.2100","base_est_val":"1.2355","est_err":"2.11%"}},{"id":"161726","cell":{"price_dt":"2015-08-17","base_fund_id":"161726","a_price":"0.874","a_price_increase_rt":"1.04%","a_profit_rt":"5.766%","a_amount":"6374","a_amount_increase":"-185","a_amount_increase_rt":"-2.821%","a_discount_rt":"13.120%","b_discount_rt":"5.400%","b_net_leverage_rt":"1.639","b_price_leverage_rt":"1.555","base_discount_rt":"-1.822%","net_value":"1.2900","base_est_val":"1.2794","est_err":"-0.82%"}},{"id":"161726","cell":{"price_dt":"2015-08-14","base_fund_id":"161726","a_price":"0.865","a_price_increase_rt":"0.35%","a_profit_rt":"5.820%","a_amount":"6559","a_amount_increase":"37","a_amount_increase_rt":"0.567%","a_discount_rt":"13.930%","b_discount_rt":"6.321%","b_net_leverage_rt":"1.669","b_price_leverage_rt":"1.569","base_discount_rt":"-1.794%","net_value":"1.2540","base_est_val":"1.2480","est_err":"-0.48%"}},{"id":"161726","cell":{"price_dt":"2015-08-13","base_fund_id":"161726","a_price":"0.862","a_price_increase_rt":"-0.12%","a_profit_rt":"5.840%","a_amount":"6522","a_amount_increase":"-268","a_amount_increase_rt":"-3.947%","a_discount_rt":"14.230%","b_discount_rt":"9.789%","b_net_leverage_rt":"1.683","b_price_leverage_rt":"1.533","base_discount_rt":"0.040%","net_value":"1.2380","base_est_val":"1.2323","est_err":"-0.46%"}},{"id":"161726","cell":{"price_dt":"2015-08-12","base_fund_id":"161726","a_price":"0.863","a_price_increase_rt":"1.05%","a_profit_rt":"5.833%","a_amount":"6790","a_amount_increase":"245","a_amount_increase_rt":"3.743%","a_discount_rt":"14.130%","b_discount_rt":"8.455%","b_net_leverage_rt":"1.696","b_price_leverage_rt":"1.564","base_discount_rt":"-0.817%","net_value":"1.2240","base_est_val":"1.2329","est_err":"0.73%"}},{"id":"161726","cell":{"price_dt":"2015-08-11","base_fund_id":"161726","a_price":"0.854","a_price_increase_rt":"0.47%","a_profit_rt":"5.895%","a_amount":"6545","a_amount_increase":"12","a_amount_increase_rt":"0.184%","a_discount_rt":"15.020%","b_discount_rt":"9.766%","b_net_leverage_rt":"1.672","b_price_leverage_rt":"1.523","base_discount_rt":"-0.200%","net_value":"1.2500","base_est_val":"1.2532","est_err":"0.26%"}},{"id":"161726","cell":{"price_dt":"2015-08-10","base_fund_id":"161726","a_price":"0.850","a_price_increase_rt":"-1.73%","a_profit_rt":"5.923%","a_amount":"6533","a_amount_increase":"7","a_amount_increase_rt":"0.107%","a_discount_rt":"15.420%","b_discount_rt":"10.467%","b_net_leverage_rt":"1.662","b_price_leverage_rt":"1.504","base_discount_rt":"0.158%","net_value":"1.2620","base_est_val":"1.2419","est_err":"-1.59%"}},{"id":"161726","cell":{"price_dt":"2015-08-07","base_fund_id":"161726","a_price":"0.865","a_price_increase_rt":"-1.14%","a_profit_rt":"5.813%","a_amount":"6526","a_amount_increase":"-48","a_amount_increase_rt":"-0.730%","a_discount_rt":"13.840%","b_discount_rt":"8.618%","b_net_leverage_rt":"1.715","b_price_leverage_rt":"1.579","base_discount_rt":"-0.748%","net_value":"1.2040","base_est_val":"1.1951","est_err":"-0.74%"}},{"id":"161726","cell":{"price_dt":"2015-08-06","base_fund_id":"161726","a_price":"0.875","a_price_increase_rt":"0.00%","a_profit_rt":"5.746%","a_amount":"6574","a_amount_increase":"-56","a_amount_increase_rt":"-0.845%","a_discount_rt":"12.850%","b_discount_rt":"9.610%","b_net_leverage_rt":"1.754","b_price_leverage_rt":"1.600","base_discount_rt":"-0.043%","net_value":"1.1680","base_est_val":"1.1720","est_err":"0.34%"}},{"id":"161726","cell":{"price_dt":"2015-08-05","base_fund_id":"161726","a_price":"0.875","a_price_increase_rt":"1.04%","a_profit_rt":"5.746%","a_amount":"6630","a_amount_increase":"-106","a_amount_increase_rt":"-1.574%","a_discount_rt":"12.850%","b_discount_rt":"8.029%","b_net_leverage_rt":"1.733","b_price_leverage_rt":"1.604","base_discount_rt":"-0.800%","net_value":"1.1870","base_est_val":"1.1894","est_err":"0.20%"}},{"id":"161726","cell":{"price_dt":"2015-08-04","base_fund_id":"161726","a_price":"0.866","a_price_increase_rt":"-2.81%","a_profit_rt":"5.807%","a_amount":"6736","a_amount_increase":"-416","a_amount_increase_rt":"-5.817%","a_discount_rt":"13.750%","b_discount_rt":"6.071%","b_net_leverage_rt":"1.717","b_price_leverage_rt":"1.619","base_discount_rt":"-2.205%","net_value":"1.2020","base_est_val":"1.1871","est_err":"-1.24%"}},{"id":"161726","cell":{"price_dt":"2015-08-03","base_fund_id":"161726","a_price":"0.891","a_price_increase_rt":"3.97%","a_profit_rt":"5.643%","a_amount":"7152","a_amount_increase":"-175","a_amount_increase_rt":"-2.388%","a_discount_rt":"11.250%","b_discount_rt":"4.328%","b_net_leverage_rt":"1.776","b_price_leverage_rt":"1.702","base_discount_rt":"-2.480%","net_value":"1.1490","base_est_val":"1.1469","est_err":"-0.18%"}},{"id":"161726","cell":{"price_dt":"2015-07-31","base_fund_id":"161726","a_price":"0.857","a_price_increase_rt":"0.82%","a_profit_rt":"5.861%","a_amount":"7327","a_amount_increase":"-303","a_amount_increase_rt":"-3.971%","a_discount_rt":"14.560%","b_discount_rt":"7.191%","b_net_leverage_rt":"1.751","b_price_leverage_rt":"1.634","base_discount_rt":"-2.139%","net_value":"1.1690","base_est_val":"1.1681","est_err":"-0.08%"}},{"id":"161726","cell":{"price_dt":"2015-07-30","base_fund_id":"161726","a_price":"0.850","a_price_increase_rt":"1.19%","a_profit_rt":"5.910%","a_amount":"7630","a_amount_increase":"-28","a_amount_increase_rt":"-0.366%","a_discount_rt":"15.250%","b_discount_rt":"9.471%","b_net_leverage_rt":"1.748","b_price_leverage_rt":"1.597","base_discount_rt":"-1.109%","net_value":"1.1720","base_est_val":"1.1922","est_err":"1.72%"}},{"id":"161726","cell":{"price_dt":"2015-07-29","base_fund_id":"161726","a_price":"0.840","a_price_increase_rt":"-1.18%","a_profit_rt":"5.980%","a_amount":"7658","a_amount_increase":"-296","a_amount_increase_rt":"-3.721%","a_discount_rt":"16.250%","b_discount_rt":"8.014%","b_net_leverage_rt":"1.699","b_price_leverage_rt":"1.573","base_discount_rt":"-1.969%","net_value":"1.2190","base_est_val":"1.1975","est_err":"-1.76%"}},{"id":"161726","cell":{"price_dt":"2015-07-28","base_fund_id":"161726","a_price":"0.850","a_price_increase_rt":"-1.85%","a_profit_rt":"5.910%","a_amount":"7954","a_amount_increase":"-575","a_amount_increase_rt":"-6.742%","a_discount_rt":"15.250%","b_discount_rt":"10.744%","b_net_leverage_rt":"1.754","b_price_leverage_rt":"1.583","base_discount_rt":"-0.428%","net_value":"1.1670","base_est_val":"1.1795","est_err":"1.07%"}},{"id":"161726","cell":{"price_dt":"2015-07-27","base_fund_id":"161726","a_price":"0.866","a_price_increase_rt":"3.71%","a_profit_rt":"5.800%","a_amount":"8529","a_amount_increase":"-238","a_amount_increase_rt":"-2.715%","a_discount_rt":"13.660%","b_discount_rt":"14.742%","b_net_leverage_rt":"1.728","b_price_leverage_rt":"1.506","base_discount_rt":"2.773%","net_value":"1.1900","base_est_val":"1.2314","est_err":"3.48%"}},{"id":"161726","cell":{"price_dt":"2015-07-24","base_fund_id":"161726","a_price":"0.835","a_price_increase_rt":"1.83%","a_profit_rt":"6.009%","a_amount":"8767","a_amount_increase":"-18","a_amount_increase_rt":"-0.205%","a_discount_rt":"16.670%","b_discount_rt":"8.871%","b_net_leverage_rt":"1.622","b_price_leverage_rt":"1.489","base_discount_rt":"-0.918%","net_value":"1.3070","base_est_val":"1.3164","est_err":"0.72%"}},{"id":"161726","cell":{"price_dt":"2015-07-23","base_fund_id":"161726","a_price":"0.820","a_price_increase_rt":"-0.85%","a_profit_rt":"6.120%","a_amount":"8785","a_amount_increase":"110","a_amount_increase_rt":"1.268%","a_discount_rt":"18.160%","b_discount_rt":"8.233%","b_net_leverage_rt":"1.602","b_price_leverage_rt":"1.480","base_discount_rt":"-1.688%","net_value":"1.3330","base_est_val":"1.3185","est_err":"-1.09%"}},{"id":"161726","cell":{"price_dt":"2015-07-22","base_fund_id":"161726","a_price":"0.827","a_price_increase_rt":"-2.48%","a_profit_rt":"6.068%","a_amount":"8675","a_amount_increase":"54","a_amount_increase_rt":"0.626%","a_discount_rt":"17.470%","b_discount_rt":"13.068%","b_net_leverage_rt":"1.633","b_price_leverage_rt":"1.444","base_discount_rt":"1.237%","net_value":"1.2930","base_est_val":"1.2873","est_err":"-0.44%"}},{"id":"161726","cell":{"price_dt":"2015-07-21","base_fund_id":"161726","a_price":"0.848","a_price_increase_rt":"-0.59%","a_profit_rt":"5.917%","a_amount":"8621","a_amount_increase":"-175","a_amount_increase_rt":"-1.990%","a_discount_rt":"15.370%","b_discount_rt":"10.038%","b_net_leverage_rt":"1.637","b_price_leverage_rt":"1.487","base_discount_rt":"0.155%","net_value":"1.2880","base_est_val":"1.2836","est_err":"-0.34%"}},{"id":"161726","cell":{"price_dt":"2015-07-20","base_fund_id":"161726","a_price":"0.853","a_price_increase_rt":"-1.50%","a_profit_rt":"5.882%","a_amount":"8796","a_amount_increase":"-670","a_amount_increase_rt":"-7.078%","a_discount_rt":"14.870%","b_discount_rt":"7.019%","b_net_leverage_rt":"1.670","b_price_leverage_rt":"1.560","base_discount_rt":"-1.761%","net_value":"1.2490","base_est_val":"1.2442","est_err":"-0.38%"}},{"id":"161726","cell":{"price_dt":"2015-07-17","base_fund_id":"161726","a_price":"0.866","a_price_increase_rt":"0.35%","a_profit_rt":"5.787%","a_amount":"9466","a_amount_increase":"-536","a_amount_increase_rt":"-5.359%","a_discount_rt":"13.490%","b_discount_rt":"1.654%","b_net_leverage_rt":"1.690","b_price_leverage_rt":"1.662","base_discount_rt":"-4.527%","net_value":"1.2260","base_est_val":"1.2094","est_err":"-1.35%"}},{"id":"161726","cell":{"price_dt":"2015-07-16","base_fund_id":"161726","a_price":"0.863","a_price_increase_rt":"1.77%","a_profit_rt":"5.807%","a_amount":"10002","a_amount_increase":"-1557","a_amount_increase_rt":"-13.470%","a_discount_rt":"13.790%","b_discount_rt":"3.873%","b_net_leverage_rt":"1.775","b_price_leverage_rt":"1.709","base_discount_rt":"-3.839%","net_value":"1.1460","base_est_val":"1.1396","est_err":"-0.56%"}},{"id":"161726","cell":{"price_dt":"2015-07-15","base_fund_id":"161726","a_price":"0.848","a_price_increase_rt":"1.44%","a_profit_rt":"5.910%","a_amount":"11559","a_amount_increase":"-110","a_amount_increase_rt":"-0.943%","a_discount_rt":"15.280%","b_discount_rt":"10.074%","b_net_leverage_rt":"1.827","b_price_leverage_rt":"1.659","base_discount_rt":"-1.401%","net_value":"1.1060","base_est_val":"1.1162","est_err":"0.92%"}},{"id":"161726","cell":{"price_dt":"2015-07-14","base_fund_id":"161726","a_price":"0.836","a_price_increase_rt":"-7.11%","a_profit_rt":"5.996%","a_amount":"11669","a_amount_increase":"4050","a_amount_increase_rt":"53.157%","a_discount_rt":"16.480%","b_discount_rt":"-2.665%","b_net_leverage_rt":"1.741","b_price_leverage_rt":"1.789","base_discount_rt":"-8.546%","net_value":"1.1760","base_est_val":"1.1586","est_err":"-1.48%"}},{"id":"161726","cell":{"price_dt":"2015-07-13","base_fund_id":"161726","a_price":"0.900","a_price_increase_rt":"-10.00%","a_profit_rt":"5.568%","a_amount":"7619","a_amount_increase":"-21258","a_amount_increase_rt":"-73.616%","a_discount_rt":"10.090%","b_discount_rt":"-1.240%","b_net_leverage_rt":"1.827","b_price_leverage_rt":"1.850","base_discount_rt":"-5.223%","net_value":"1.1052","base_est_val":"1.1052","est_err":"0.00%"}},{"id":"161726","cell":{"price_dt":"2015-07-10","base_fund_id":"161726","a_price":"0.851","a_price_increase_rt":"0.00%","a_profit_rt":"5.883%","a_amount":"28877","a_amount_increase":"-","a_amount_increase_rt":"0.000%","a_discount_rt":"14.900%","b_discount_rt":"-58.133%","b_net_leverage_rt":"1.924","b_price_leverage_rt":"4.595","base_discount_rt":"-37.359%","net_value":"1.0409","base_est_val":"1.0409","est_err":"0.00%"}},{"id":"161726","cell":{"price_dt":"2015-07-09","base_fund_id":"161726","a_price":"0.851","a_price_increase_rt":"9.95%","a_profit_rt":"5.883%","a_amount":"28877","a_amount_increase":"-1484","a_amount_increase_rt":"-4.888%","a_discount_rt":"14.900%","b_discount_rt":"70.943%","b_net_leverage_rt":"4.774","b_price_leverage_rt":"2.793","base_discount_rt":"3.075%","net_value":"0.6325","base_est_val":"0.6325","est_err":"0.00%"}},{"id":"161726","cell":{"price_dt":"2015-07-08","base_fund_id":"161726","a_price":"0.774","a_price_increase_rt":"-8.94%","a_profit_rt":"6.520%","a_amount":"30361","a_amount_increase":"-184","a_amount_increase_rt":"-0.602%","a_discount_rt":"23.060%","b_discount_rt":"121.226%","b_net_leverage_rt":"5.745","b_price_leverage_rt":"2.597","base_discount_rt":"2.053%","net_value":"0.6090","base_est_val":"0.6220","est_err":"2.13%"}},{"id":"161726","cell":{"price_dt":"2015-07-07","base_fund_id":"161726","a_price":"0.850","a_price_increase_rt":"2.53%","a_profit_rt":"5.932%","a_amount":"30545","a_amount_increase":"-105","a_amount_increase_rt":"-0.343%","a_discount_rt":"15.510%","b_discount_rt":"101.938%","b_net_leverage_rt":"4.899","b_price_leverage_rt":"2.426","base_discount_rt":"8.465%","net_value":"0.6320","base_est_val":"0.6407","est_err":"1.38%"}},{"id":"161726","cell":{"price_dt":"2015-07-06","base_fund_id":"161726","a_price":"0.829","a_price_increase_rt":"2.22%","a_profit_rt":"6.083%","a_amount":"30650","a_amount_increase":"-4","a_amount_increase_rt":"-0.013%","a_discount_rt":"17.590%","b_discount_rt":"72.321%","b_net_leverage_rt":"3.994","b_price_leverage_rt":"2.318","base_discount_rt":"4.918%","net_value":"0.6710","base_est_val":"0.6754","est_err":"0.66%"}},{"id":"161726","cell":{"price_dt":"2015-07-03","base_fund_id":"161726","a_price":"0.811","a_price_increase_rt":"4.11%","a_profit_rt":"6.212%","a_amount":"30654","a_amount_increase":"-72","a_amount_increase_rt":"-0.234%","a_discount_rt":"19.300%","b_discount_rt":"34.801%","b_net_leverage_rt":"2.943","b_price_leverage_rt":"2.184","base_discount_rt":"3.561%","net_value":"0.7020","base_est_val":"0.7084","est_err":"0.91%"}},{"id":"161726","cell":{"price_dt":"2015-07-02","base_fund_id":"161726","a_price":"0.779","a_price_increase_rt":"-1.39%","a_profit_rt":"6.469%","a_amount":"30726","a_amount_increase":"614","a_amount_increase_rt":"2.039%","a_discount_rt":"22.490%","b_discount_rt":"49.686%","b_net_leverage_rt":"3.107","b_price_leverage_rt":"2.076","base_discount_rt":"0.742%","net_value":"0.7410","base_est_val":"0.7492","est_err":"1.11%"}},{"id":"161726","cell":{"price_dt":"2015-07-01","base_fund_id":"161726","a_price":"0.790","a_price_increase_rt":"2.20%","a_profit_rt":"6.379%","a_amount":"30112","a_amount_increase":"22","a_amount_increase_rt":"0.073%","a_discount_rt":"21.390%","b_discount_rt":"39.823%","b_net_leverage_rt":"2.779","b_price_leverage_rt":"1.987","base_discount_rt":"0.637%","net_value":"0.7850","base_est_val":"0.7922","est_err":"0.92%"}},{"id":"161726","cell":{"price_dt":"2015-06-30","base_fund_id":"161726","a_price":"0.773","a_price_increase_rt":"-3.13%","a_profit_rt":"6.520%","a_amount":"30090","a_amount_increase":"43","a_amount_increase_rt":"0.143%","a_discount_rt":"23.080%","b_discount_rt":"36.933%","b_net_leverage_rt":"2.573","b_price_leverage_rt":"1.879","base_discount_rt":"0.243%","net_value":"0.8220","base_est_val":"0.8109","est_err":"-1.35%"}},{"id":"161726","cell":{"price_dt":"2015-06-29","base_fund_id":"161726","a_price":"0.798","a_price_increase_rt":"-2.09%","a_profit_rt":"6.306%","a_amount":"30047","a_amount_increase":"394","a_amount_increase_rt":"1.329%","a_discount_rt":"20.520%","b_discount_rt":"40.621%","b_net_leverage_rt":"2.752","b_price_leverage_rt":"1.957","base_discount_rt":"1.701%","net_value":"0.7886","base_est_val":"0.7886","est_err":"0.00%"}},{"id":"161726","cell":{"price_dt":"2015-06-26","base_fund_id":"161726","a_price":"0.815","a_price_increase_rt":"2.90%","a_profit_rt":"6.473%","a_amount":"29653","a_amount_increase":"-58","a_amount_increase_rt":"-0.195%","a_discount_rt":"18.820%","b_discount_rt":"34.132%","b_net_leverage_rt":"2.503","b_price_leverage_rt":"1.866","base_discount_rt":"2.333%","net_value":"0.8360","base_est_val":"0.8430","est_err":"0.84%"}},{"id":"161726","cell":{"price_dt":"2015-06-25","base_fund_id":"161726","a_price":"0.792","a_price_increase_rt":"1.41%","a_profit_rt":"6.662%","a_amount":"29711","a_amount_increase":"82","a_amount_increase_rt":"0.277%","a_discount_rt":"21.120%","b_discount_rt":"24.687%","b_net_leverage_rt":"2.258","b_price_leverage_rt":"1.811","base_discount_rt":"-0.832%","net_value":"0.9010","base_est_val":"0.9036","est_err":"0.29%"}},{"id":"161726","cell":{"price_dt":"2015-06-24","base_fund_id":"161726","a_price":"0.781","a_price_increase_rt":"0.26%","a_profit_rt":"6.757%","a_amount":"29629","a_amount_increase":"80","a_amount_increase_rt":"0.271%","a_discount_rt":"22.210%","b_discount_rt":"24.221%","b_net_leverage_rt":"2.204","b_price_leverage_rt":"1.774","base_discount_rt":"-1.143%","net_value":"0.9190","base_est_val":"0.9182","est_err":"-0.09%"}},{"id":"161726","cell":{"price_dt":"2015-06-23","base_fund_id":"161726","a_price":"0.779","a_price_increase_rt":"-0.38%","a_profit_rt":"6.774%","a_amount":"29549","a_amount_increase":"-160","a_amount_increase_rt":"-0.539%","a_discount_rt":"22.410%","b_discount_rt":"27.419%","b_net_leverage_rt":"2.246","b_price_leverage_rt":"1.762","base_discount_rt":"-0.221%","net_value":"0.9050","base_est_val":"0.9035","est_err":"-0.17%"}},{"id":"161726","cell":{"price_dt":"2015-06-19","base_fund_id":"161726","a_price":"0.782","a_price_increase_rt":"0.13%","a_profit_rt":"6.739%","a_amount":"29709","a_amount_increase":"-513","a_amount_increase_rt":"-1.697%","a_discount_rt":"22.030%","b_discount_rt":"27.643%","b_net_leverage_rt":"2.278","b_price_leverage_rt":"1.784","base_discount_rt":"-0.224%","net_value":"0.8940","base_est_val":"0.8992","est_err":"0.58%"}},{"id":"161726","cell":{"price_dt":"2015-06-18","base_fund_id":"161726","a_price":"0.781","a_price_increase_rt":"0.13%","a_profit_rt":"6.748%","a_amount":"30222","a_amount_increase":"351","a_amount_increase_rt":"1.175%","a_discount_rt":"22.130%","b_discount_rt":"24.005%","b_net_leverage_rt":"2.141","b_price_leverage_rt":"1.727","base_discount_rt":"-0.584%","net_value":"0.9410","base_est_val":"0.9474","est_err":"0.68%"}},{"id":"161726","cell":{"price_dt":"2015-06-17","base_fund_id":"161726","a_price":"0.780","a_price_increase_rt":"-0.26%","a_profit_rt":"6.757%","a_amount":"29871","a_amount_increase":"521","a_amount_increase_rt":"1.775%","a_discount_rt":"22.230%","b_discount_rt":"22.106%","b_net_leverage_rt":"2.046","b_price_leverage_rt":"1.675","base_discount_rt":"-0.561%","net_value":"0.9810","base_est_val":"0.9773","est_err":"-0.38%"}},{"id":"161726","cell":{"price_dt":"2015-06-16","base_fund_id":"161726","a_price":"0.782","a_price_increase_rt":"-0.26%","a_profit_rt":"6.739%","a_amount":"29350","a_amount_increase":"-883","a_amount_increase_rt":"-2.921%","a_discount_rt":"22.030%","b_discount_rt":"25.674%","b_net_leverage_rt":"2.082","b_price_leverage_rt":"1.657","base_discount_rt":"0.881%","net_value":"0.9650","base_est_val":"0.9733","est_err":"0.86%"}},{"id":"161726","cell":{"price_dt":"2015-06-15","base_fund_id":"161726","a_price":"0.784","a_price_increase_rt":"0.13%","a_profit_rt":"6.722%","a_amount":"30233","a_amount_increase":"-1129","a_amount_increase_rt":"-3.600%","a_discount_rt":"21.830%","b_discount_rt":"21.896%","b_net_leverage_rt":"1.980","b_price_leverage_rt":"1.625","base_discount_rt":"0.247%","net_value":"1.0130","base_est_val":"1.0234","est_err":"1.03%"}},{"id":"161726","cell":{"price_dt":"2015-06-12","base_fund_id":"161726","a_price":"0.783","a_price_increase_rt":"0.00%","a_profit_rt":"6.722%","a_amount":"31362","a_amount_increase":"78","a_amount_increase_rt":"0.249%","a_discount_rt":"21.860%","b_discount_rt":"15.330%","b_net_leverage_rt":"1.893","b_price_leverage_rt":"1.641","base_discount_rt":"-2.213%","net_value":"1.0620","base_est_val":"1.0617","est_err":"-0.03%"}},{"id":"161726","cell":{"price_dt":"2015-06-11","base_fund_id":"161726","a_price":"0.783","a_price_increase_rt":"1.16%","a_profit_rt":"6.722%","a_amount":"31284","a_amount_increase":"8137","a_amount_increase_rt":"35.154%","a_discount_rt":"21.860%","b_discount_rt":"17.902%","b_net_leverage_rt":"1.906","b_price_leverage_rt":"1.617","base_discount_rt":"-0.996%","net_value":"1.0540","base_est_val":"1.0532","est_err":"-0.08%"}},{"id":"161726","cell":{"price_dt":"2015-06-10","base_fund_id":"161726","a_price":"0.774","a_price_increase_rt":"-0.39%","a_profit_rt":"6.801%","a_amount":"23147","a_amount_increase":"7658","a_amount_increase_rt":"49.442%","a_discount_rt":"22.750%","b_discount_rt":"20.588%","b_net_leverage_rt":"1.951","b_price_leverage_rt":"1.618","base_discount_rt":"-0.535%","net_value":"1.0280","base_est_val":"1.0314","est_err":"0.33%"}},{"id":"161726","cell":{"price_dt":"2015-06-09","base_fund_id":"161726","a_price":"0.777","a_price_increase_rt":"-4.19%","a_profit_rt":"6.774%","a_amount":"15489","a_amount_increase":"6390","a_amount_increase_rt":"70.227%","a_discount_rt":"22.460%","b_discount_rt":"30.655%","b_net_leverage_rt":"1.994","b_price_leverage_rt":"1.526","base_discount_rt":"4.179%","net_value":"1.0050","base_est_val":"1.0077","est_err":"0.27%"}},{"id":"161726","cell":{"price_dt":"2015-06-08","base_fund_id":"161726","a_price":"0.811","a_price_increase_rt":"-9.99%","a_profit_rt":"6.489%","a_amount":"9099","a_amount_increase":"-","a_amount_increase_rt":"0.000%","a_discount_rt":"19.060%","b_discount_rt":"25.686%","b_net_leverage_rt":"1.982","b_price_leverage_rt":"1.577","base_discount_rt":"3.511%","net_value":"1.0110","base_est_val":"1.0132","est_err":"0.22%"}},{"id":"161726","cell":{"price_dt":"2015-06-05","base_fund_id":"161726","a_price":"0.901","a_price_increase_rt":"-9.99%","a_profit_rt":"5.830%","a_amount":"9099","a_amount_increase":"-","a_amount_increase_rt":"0.000%","a_discount_rt":"9.990%","b_discount_rt":"10.636%","b_net_leverage_rt":"1.951","b_price_leverage_rt":"1.763","base_discount_rt":"0.584%","net_value":"1.0270","base_est_val":"1.0300","est_err":"0.29%"}},{"id":"161726","cell":{"price_dt":"2015-06-04","base_fund_id":"161726","a_price":"1.000","a_price_increase_rt":"0.00%","a_profit_rt":"5.260%","a_amount":"9099","a_amount_increase":"-","a_amount_increase_rt":"0.000%","a_discount_rt":"0.100%","b_discount_rt":"-5.571%","b_net_leverage_rt":"1.945","b_price_leverage_rt":"2.060","base_discount_rt":"-2.913%","net_value":"1.0300","base_est_val":"1.0010","est_err":"-2.82%"}}],"total":213}
